Workbook
Name for_fulltext_screening: 'Full Text Screening'!$A$1:$E$123
Name SLR_Include_In_Review: review_zotero_export!$A$1:$CH$43

Sheet Title Abstract Screening
A1: Screening | B1: Notes | C1: Key | D1: Item Type | E1: Publication Year | F1: Author | G1: Title | H1: Publication Title | I1: ISBN | J1: ISSN | K1: DOI | L1: Url | M1: Abstract Note | N1: Date | O1: Date Added | P1: Date Modified | Q1: Access Date | R1: Pages | S1: Num Pages | T1: Issue | U1: Volume | V1: Number Of Volumes | W1: Journal Abbreviation | X1: Short Title | Y1: Series | Z1: Series Number | AA1: Series Text | AB1: Series Title | AC1: Publisher | AD1: Place | AE1: Language | AF1: Rights | AG1: Type | AH1: Archive | AI1: Archive Location | AJ1: Library Catalog | AK1: Call Number | AL1: Extra | AM1: Notes | AN1: File Attachments | AO1: Link Attachments | AP1: Manual Tags | AQ1: Automatic Tags | AR1: Editor | AS1: Series Editor | AT1: Translator | AU1: Contributor | AV1: Attorney Agent | AW1: Book Author | AX1: Cast Member | AY1: Commenter | AZ1: Composer | BA1: Cosponsor | BB1: Counsel | BC1: Interviewer | BD1: Producer | BE1: Recipient | BF1: Reviewed Author | BG1: Scriptwriter | BH1: Words By | BI1: Guest | BJ1: Number | BK1: Edition | BL1: Running Time | BM1: Scale | BN1: Medium | BO1: Artwork Size | BP1: Filing Date | BQ1: Application Number | BR1: Assignee | BS1: Issuing Authority | BT1: Country | BU1: Meeting Name | BV1: Conference Name | BW1: Court | BX1: References | BY1: Reporter | BZ1: Legal Status | CA1: Priority Numbers | CB1: Programming Language | CC1: Version | CD1: System | CE1: Code | CF1: Code Number | CG1: Section | CH1: Session | CI1: Committee | CJ1: History | CK1: Legislative Body
A2: exclude | B2: only questionnaires | C2: 2SJXTDKX | D2: conferencePaper | E2: 2019 | F2: Abdi Oskouie, Mina; Boulanger, Pierre | G2: Using Proxy Haptic for a Pointing Task in the Virtual World: A Usability Study | H2: Augmented Reality, Virtual Reality, and Computer Graphics: 6th International Conference, AVR 2019, Santa Maria al Bagno, Italy, June 24–27, 2019, Proceedings, Part I | I2: 978-3-030-25964-8 | K2: 10.1007/978-3-030-25965-5_21 | L2: https://doi.org/10.1007/978-3-030-25965-5_21 | M2: Virtual Reality (VR) applications are getting progressively more popular in many disciplines. This is mainly due to (1) technological advancement in rendering images and sounds, and (2) immersive experience of VR which intensifies users’ engagement leading to improved joy, sense of presence and success. Although VR creates a realistic experience by simulating visual and auditory sense, it ignores other human senses. The absence of haptic feedback in Virtual Environments (VE) can impair users’ engagement. Our objective is to provide haptic feedback in VE using the most affordable method, proxy haptics. Proxies are physical objects which are co-registered with virtual objects in a way that by touching the proxies, users see their virtual hand touching the virtual objects. So, the haptic feedback will be applied to users’ hands by touching the proxies. The important question which arises here is: what are the influences of providing haptic feedback on users’ performance and usability? In this work, we have designed an experiment in Virtual Reality to answer this question. In the virtual environment, we presented a keyboard with touchable keys and asked our participants to type three words using the keyboard. They repeated the experiment twice: once they used their own hands and pressed the keys and once they used VR controllers for typing. Our results show that participants can type words with fewer errors when they are using their own hands while they found VR controllers easier to use. | N2: 2019 | O2: 45783.306 | P2: 45783.306 | R2: 292–299 | AC2: Springer-Verlag | AD2: Berlin, Heidelberg | AL2: event-place: Santa Maria al Bagno, Italy | AP2: Virtual Reality; Usability test; Passive haptic; Sense of touch
A3: exclude | B3: no AR/VR | C3: IRY3WI6P | D3: conferencePaper | E3: 2012 | F3: Abdul Rahim, Elin; Duenser, Andreas; Billinghurst, Mark; Herritsch, Alfred; Unsworth, Keith; Mckinnon, Alan; Gostomski, Peter | G3: A desktop virtual reality application for chemical and process engineering education | H3: Proceedings of the 24th Australian Computer-Human Interaction Conference | I3: 978-1-4503-1438-1 | K3: 10.1145/2414536.2414537 | L3: https://doi.org/10.1145/2414536.2414537 | M3: A desktop Virtual Reality (VR) application of a skim milk powder process has been developed. The goal was to use this application as a learning resource to expose students to processing plant environments, which are becoming increasingly difficult to visit due to availability and safety reasons. The VR application comprises 360° panorama images of the milk powder process plant, process flow diagrams (PFD), piping and instrumentation diagrams (P&amp;ID), 3D drawings and additional materials such as supplemental text, videos and animations. This paper describes the VR application as well as an evaluation of the application. The results of this study show that the application was easy to use and the users were satisfied with it. The design recommendations for the development of similar VR learning applications are also discussed in this paper. | N3: 2012 | O3: 45783.306 | P3: 45783.306 | R3: 1–8 | Y3: OzCHI '12 | AC3: Association for Computing Machinery | AD3: New York, NY, USA | AL3: event-place: Melbourne, Australia | AP3: usability; virtual reality; evaluation; educational software; engineering
A4: exclude | B4: only questionnaires | C4: CFXDR833 | D4: conferencePaper | E4: 2012 | F4: Abu Shanab, Shatha; Odeh, Salaheddin; Hodrob, Rami; Anabtawi, Mahasen | G4: Augmented reality internet labs versus hands-on and virtual labs: A comparative study | H4: Proceedings of 2012 International Conference on Interactive Mobile and Computer Aided Learning (IMCL) | I4: 978-1-4673-4925-3 978-1-4673-4924-6 978-1-4673-4923-9 | K4: 10.1109/IMCL.2012.6396444 | L4: http://ieeexplore.ieee.org/document/6396444/ | N4: 2012-11 | O4: 45783.312 | P4: 45783.312 | Q4: 45783.312 | R4: 17-21 | X4: Augmented reality internet labs versus hands-on and virtual labs | AC4: IEEE | AD4: Amman, Jordan | AJ4: DOI.org (Crossref) | BV4: 2012 International Conference on Interactive Mobile and Computer Aided Learning (IMCL)
A5: for-fulltext | B5: physiological factors | C5: WBUZ3SQ5 | D5: conferencePaper | E5: 2023 | F5: Döllinger, Nina; Beck, Matthias; Wolf, Erik; Mal, David; Botsch, Mario; Latoschik, Marc Erich; Wienrich, Carolin | G5: “If It’s Not Me It Doesn’t Make a Difference” - The Impact of Avatar Personalization on user Experience and Body Awareness in Virtual Reality | H5: 2023 IEEE International Symposium on Mixed and Augmented Reality (ISMAR) | I5: 979-8-3503-2838-7 | K5: 10.1109/ISMAR59233.2023.00063 | L5: https://ieeexplore.ieee.org/document/10316447/ | N5: 45215 | O5: 45783.312 | P5: 45783.312 | Q5: 45783.312 | R5: 483-492 | AC5: IEEE | AD5: Sydney, Australia | AJ5: DOI.org (Crossref) | AN5: /Users/dennis/Zotero/storage/EVB7ZX4B/Döllinger et al. - 2023 - “If It’s Not Me It Doesn’t Make a Difference” - The Impact of Avatar Personalization on user Experie.pdf | BV5: 2023 IEEE International Symposium on Mixed and Augmented Reality (ISMAR)
A6: exclude | B6: irrelevant | C6: Q6JQP3VK | D6: conferencePaper | E6: 2024 | F6: Adriana, M.; Daniel, C.; Cosmin, M. | G6: MediQApp: Advanced Integration of Risk Digitization in E-Health and E-Learning Domains | H6: IFMBE Proc. | I6: 16800737 (ISSN); 978-303162501-5 (ISBN) | K6: 10.1007/978-3-031-62502-2_42 | L6: https://www.scopus.com/inward/record.uri?eid=2-s2.0-85210094429&doi=10.1007%2f978-3-031-62502-2_42&partnerID=40&md5=4dcf2e943a6778fb103f9eb3e7756669 | M6: This scientific research explores the integration of advanced digital automation in healthcare, focusing on its application in mitigating clinical risks across various surgical disciplines. The latest MediQApp (version 5.0) represents a significant advancement in this field, effectively combining E-Health with ELearning. This version has undergone comprehensive evaluations through document analysis, quality management audits, clinical audits, direct observation of hospital activities, process simulations, testing, and extensive user feedback. These evaluations have underscored its efficacy in streamlining risk management and improving operational efficiency within healthcare settings. MediQApp has particularly excelled in user experience, offering an intuitive interface and easy navigation, significantly enhancing user satisfaction among healthcare professionals. The application also shows promise in expanding its capabilities to include predictive analytics, VR/AR integration for training and patient care, and blockchain technology for enhanced data security, positioning it as a pivotal tool in the ongoing digital transformation of the healthcare industry. © The Author(s), under exclusive license to Springer Nature Switzerland AG 2024. | N6: 2024 | O6: 45783.3 | P6: 45783.3 | R6: 359-366 | U6: 109 | AC6: Springer Science and Business Media Deutschland GmbH | AE6: English | AH6: Scopus | AL6: Journal Abbreviation: IFMBE Proc. | AP6: Risk management; E - learning; Clinical research; Electronic health record; Analysis; Analyze; Clinical risks; Digital automation; Digitisation; E health; E-Health; E-Learning; eHealth; ITS applications; Medical Application; Mediqapp; MediQApp; Process Simulation; Process simulations; Scientific researches | AR6: Costin H.-N.; Petroiu G.G.; Magjarevic R. | BV6: IFMBE Proceedings
A7: for-fulltext | B7: usability evaluation unclear, read fulltext | C7: IDTU5H7Q | D7: conferencePaper | E7: 2010 | F7: Nakamura, Ricardo; Lago, Lucas L. M.; Carneiro, Alexandre B.; Cunha, Anderson J. C.; Ortega, Fábio J. M.; Bernardes, João L.; Tori, Romero | G7: 3PI experiment: immersion in third-person view | H7: Proceedings of the 5th ACM SIGGRAPH Symposium on Video Games | I7: 978-1-4503-0097-1 | K7: 10.1145/1836135.1836142 | L7: https://doi.org/10.1145/1836135.1836142 | M7: In this paper, we present the results of the "3PI Experiment" project. The objective of this project is to propose and evaluate an immersive interface based on a third-person view from a video camera, that can be used in augmented reality games. Since this type of interface has not been explored in games, a prototype involving interaction through navigation was developed and employed to assess the impact of the proposed interface on gameplay experience. Different user interface evaluation methods such as cognitive walkthroughs, automatic data collection and questionnaires were combined. It was possible to determine that the proposed interface caused no significant discomfort and had a short learning time, making it suitable for use in games. | N7: 2010 | O7: 45783.306 | P7: 45783.342 | R7: 43–48 | Y7: Sandbox '10 | AC7: Association for Computing Machinery | AD7: New York, NY, USA | AL7: event-place: Los Angeles, California | AP7: Virtual reality; augmented reality; Augmented reality; Immersive; User interfaces; User experience; Interactive computer graphics; Gameplay; Augmented-reality games; Automatic data collection; Game user experience; Interface evaluation; Learning time; User interface evaluation; Video cameras; Walkthroughs; game user experience; user interface evaluation
A8: exclude | B8: only questionnaires | C8: ZF82HSQR | D8: journalArticle | E8: 2024 | F8: Afyouni, Imad; Lataifeh, Mohammed; Afrah, Zulaiha; Ahmed, Naveed | G8: Usability Evaluation of Handheld and Wearable AR devices: Exploring Collaboration and the Role of Physical Props | H8: Procedia Comput. Sci. | J8: 1877-0509 | K8: 10.1016/j.procs.2023.12.156 | L8: https://doi.org/10.1016/j.procs.2023.12.156 | N8: 2024-01 | O8: 45783.306 | P8: 45783.306 | R8: 48–55 | T8: C | U8: 231 | AL8: Place: NLD Publisher: Elsevier Science Publishers B. V. | AP8: Augmented Reality; Collaboration; Physical Props; User Interaction
A9: exclude | B9: only questionnaires | C9: MKLZC2Z8 | D9: conferencePaper | E9: 2024 | F9: Aguilar, Samantha D.; Qian, Chengyuan; Monjoree, Uttamasha; Burte, Heather; Liew, Jeffrey; Queck, Francis; Yasskin, Philip; Song, Dezhen; Yan, Wei | G9: AR-Classroom Usability: Implications for UX Research on AR-Enabled Educational Technologies for 3D Matrix Algebra Learning | H9: 2024 IEEE Frontiers in Education Conference (FIE) | I9: 979-8-3503-5150-7 | K9: 10.1109/FIE61694.2024.10892900 | L9: https://ieeexplore.ieee.org/document/10892900/ | N9: 45578 | O9: 45783.313 | P9: 45783.313 | Q9: 45783.313 | R9: 45870 | X9: AR-Classroom Usability | AC9: IEEE | AD9: Washington, DC, USA | AF9: https://doi.org/10.15223/policy-029 | AJ9: DOI.org (Crossref) | BV9: 2024 IEEE Frontiers in Education Conference (FIE)
A10: exclude | B10: only questionnaires | C10: RBIZ8XGT | D10: conferencePaper | E10: 2023 | F10: Ahmed Alnagrat, Ahmed Jamah; Ismail Alkhallas, Muhannad; Imhmed Mohamed, Abdalslam S; Che Ismail, Rizalafande; Syed Idrus, Syed Zulkarnain; Salem Saed, Halifah | G10: Virtual Reality Semiconductor Laboratory: Usability Testing to Improve User Experience (UX) in Virtual Environments | H10: 2023 IEEE 3rd International Maghreb Meeting of the Conference on Sciences and Techniques of Automatic Control and Computer Engineering (MI-STA) | I10: 979-8-3503-1989-7 | K10: 10.1109/MI-STA57575.2023.10169788 | L10: https://ieeexplore.ieee.org/document/10169788/ | N10: 45067 | O10: 45783.311 | P10: 45783.311 | Q10: 45783.311 | R10: 469-473 | X10: Virtual Reality Semiconductor Laboratory | AC10: IEEE | AD10: Benghazi, Libya | AF10: https://doi.org/10.15223/policy-029 | AJ10: DOI.org (Crossref) | BV10: 2023 IEEE 3rd International Maghreb Meeting of the Conference on Sciences and Techniques of Automatic Control and Computer Engineering (MI-STA)
A11: exclude | B11: irrelevant | C11: P38B4ND4 | D11: journalArticle | E11: 2016 | F11: Aita, K.S.U.; Monte, S.J.H.; Silva, A.S.; Marroquim, M.S.C.; Coelho, A.G.B.; Sousa, L.C.D.M. | G11: Web-based ecosystem software for virtual crossmatching in transplant programs | H11: Computers in Biology and Medicine | J11: 00104825 (ISSN) | K11: 10.1016/j.compbiomed.2016.05.010 | L11: https://www.scopus.com/inward/record.uri?eid=2-s2.0-84969752647&doi=10.1016%2fj.compbiomed.2016.05.010&partnerID=40&md5=eecbc739a074507268672bd503ab0b5f | M11: Background: The compatibilities between donors and recipients are extremely important for evaluating the immunological risks of transplants. One challenge faced by data analysis tools is the transformation of complex data into simple, intuitive, and important information that can be used to resolve contemporary problems. To address this challenge, we developed the EpViX software to perform epitope reactivity analyses and automated epitope virtual crossmatching. EpViX is a facilitator of medical decision-making regarding the identification of the best donor for a high-immunologic risk recipient. The objective of this work is to describe the computational architecture of the EpViX ecosystem (http://www.epvix.com.br). Materials and methods: EpViX is a freeware on the web that was developed in the Ruby language. EpViX can be accessed from different platforms, e.g., PCs, tablets, and smartphones. It consists of an ecosystem of tools that are capable of integrating all of the stakeholders who are involved in a transplant process with a deceased donor. Results: We successfully developed a program that allows people to work collaboratively and effectively during the donation process by accurately predicting negative crossmatches, saving time and other resources. Conclusions: EpViX represents a significant breakthrough for the organ transplant process and may meet the current needs of transplant programs because it increases the chances of the allocation of low-immunologic risk donors to highly sensitized recipients and assures greater equity among the recipients on a waiting list. EpViX was duly verified and tested in terms of data security. Moreover, usability tests demonstrated that EpViX is an intuitive and easy-to-use tool. © 2016 Elsevier Ltd. | N11: 2016 | O11: 45783.3 | P11: 45783.3 | R11: 30-37 | U11: 75 | W11: Comput. Biol. Med. | AE11: English | AH11: Scopus | AL11: Publisher: Elsevier Ltd | AP11: virtual reality; Humans; Article; automation; human; procedures; time; Virtual addresses; Behavioral research; Usability tests; Decision making; Internet; priority journal; mobile application; smartphone; Ecosystems; Websites; cadaver donor; Computational architecture; computer language; computer program; Data analysis tool; Decision-making; donor; donor selection; Ecology; ecosystem; epitope; Epitope reactivity analyses; Epitopes; histocompatibility test; Histocompatibility Testing; HLA epitopes; medical decision making; Medical decision making; Metadata; Mobile Applications; organ transplantation; Organ Transplantation; Organ transplants; Programming Languages; Reactivity analysis; recipient; transplantation; Virtual crossmatch; Web-based software; Web-based softwares; World Wide Web
A12: exclude | B12: only questionnaires + interviews | C12: 5LF367YK | D12: conferencePaper | E12: 2022 | F12: Aldea, Anna; Tinga, Angelica M.; Van Zeumeren, Ilse M.; Van Nes, Nicole; Aschenbrenner, Doris | G12: Virtual Reality Tool for Human-Machine Interface Evaluation and Development (VRHEAD) | H12: 2022 IEEE Intelligent Vehicles Symposium (IV) | I12: 978-1-6654-8821-1 | K12: 10.1109/IV51971.2022.9827375 | L12: https://ieeexplore.ieee.org/document/9827375/ | N12: 44717 | O12: 45783.314 | P12: 45784.289 | Q12: 45783.314 | R12: 151-158 | AC12: IEEE | AD12: Aachen, Germany | AF12: https://doi.org/10.15223/policy-029 | AJ12: DOI.org (Crossref) | AN12: /Users/dennis/Zotero/storage/4AIENRKJ/Aldea et al. - 2022 - Virtual Reality Tool for Human-Machine Interface Evaluation and Development (VRHEAD).pdf | AP12: automated driving; Automated driving; Automation; design evaluation; Design evaluation; design for experiments; Design for experiments; Design-process; HMI; Human Centered Design; Human machine interaction; Human Machine Interface; Human-centred designs; human-machine interaction; Iterative design; iterative design process; Iterative design process; Man machine systems; mode awareness; Mode awareness; rapid prototyping; Rapid-prototyping; Vehicles; Virtual prototyping; virtual reality; Virtual reality | BV12: 2022 IEEE Intelligent Vehicles Symposium (IV)
A13: exclude | B13: literature review | C13: LRNIUZQZ | D13: conferencePaper | E13: 2024 | F13: Aldhous, Joanna; Sobolewska, Emilia; Webster, Gemma | G13: Evaluating Human Experiences of Touching Virtual Reality: A State of The Art Review | H13: 2024 IEEE International Conference on Metrology for eXtended Reality, Artificial Intelligence and Neural Engineering (MetroXRAINE) | I13: 979-8-3503-7800-9 | K13: 10.1109/MetroXRAINE62247.2024.10797081 | L13: https://ieeexplore.ieee.org/document/10797081/ | N13: 45586 | O13: 45783.313 | P13: 45783.313 | Q13: 45783.313 | R13: 243-248 | X13: Evaluating Human Experiences of Touching Virtual Reality | AC13: IEEE | AD13: St Albans, United Kingdom | AF13: https://doi.org/10.15223/policy-029 | AJ13: DOI.org (Crossref) | BV13: 2024 IEEE International Conference on Metrology for eXtended Reality, Artificial Intelligence and Neural Engineering (MetroXRAINE)
A14: exclude | B14: only questionnaires + interviews | C14: 5NVYZS9D | D14: conferencePaper | E14: 2021 | F14: Alenljung, Zackarias; Lindblom, Jessica | G14: User Experience in Augmented Reality: A Holistic Evaluation of a Prototype for Assembly Instructions | H14: Design, User Experience, and Usability: Design for Contemporary Technological Environments: 10th International Conference, DUXU 2021, Held as Part of the 23rd HCI International Conference, HCII 2021, Virtual Event, July 24–29, 2021, Proceedings, Part III | I14: 978-3-030-78226-9 | K14: 10.1007/978-3-030-78227-6_11 | L14: https://doi.org/10.1007/978-3-030-78227-6_11 | M14: Industries are under development with new upcoming tools that will further streamline the work of operators, not least in assembly. Assembly instructions are usually visualized by traditional paper or data bases. A new way of showing instruction is provided by augmented reality (AR). The focus of this paper is the user experience (UX) of AR based instructions for assembly. In order to study the UX in AR an evaluation matrix and an AR prototype has been developed and evaluated in a UX test, where data regarding both hedonic and pragmatic qualities was collected. The UX test yielded a result of three out of nine sub-goals completed while six did not. There was a general low degree of cognitive load while assembling but not low enough. However, there are promising results for AR based instructions, though the technology still needs improvement and more testing is also necessary. The assembly scenario for this study was somewhat simple and could be one reason why this study generated ambiguous results. | N14: 2021 | O14: 45783.293 | P14: 45784.355 | R14: 139–157 | U14: 12781 | AC14: Springer-Verlag | AD14: Berlin, Heidelberg | AP14: Assembly instructions; Augmented reality; Evaluation; User experience
A15: exclude | B15: irrelevant | C15: XMKNEBVW | D15: conferencePaper | E15: 2019 | F15: Ali, G.; Le, H.-Q.; Kim, J.; Hwang, S.-W.; Hwang, J.-I. | G15: Design of seamless multi-modal interaction framework for intelligent virtual agents in wearable mixed reality environment | H15: ACM Int. Conf. Proc. Ser. | I15: 978-145037159-9 (ISBN) | K15: 10.1145/3328756.3328758 | L15: https://www.scopus.com/inward/record.uri?eid=2-s2.0-85069173185&doi=10.1145%2f3328756.3328758&partnerID=40&md5=29caf4599720e0058100ba9c42524850 | M15: In this paper, we present the design of a multimodal interaction framework for intelligent virtual agents in wearable mixed reality environments, especially for interactive applications at museums, botanical gardens, and similar places. These places need engaging and no-repetitive digital content delivery to maximize user involvement. An intelligent virtual agent is a promising mode for both purposes. Premises of framework is wearable mixed reality provided by MR devices supporting spatial mapping. We envisioned a seamless interaction framework by integrating potential features of spatial mapping, virtual character animations, speech recognition, gazing, domain-specific chatbot and object recognition to enhance virtual experiences and communication between users and virtual agents. By applying a modular approach and deploying computationally intensive modules on cloud-platform, we achieved a seamless virtual experience in a device with limited resources. Human-like gaze and speech interaction with a virtual agent made it more interactive. Automated mapping of body animations with the content of a speech made it more engaging. In our tests, the virtual agents responded within 2-4 seconds after the user query. The strength of the framework is flexibility and adaptability. It can be adapted to any wearable MR device supporting spatial mapping. © 2019 Association for Computing Machinery. | N15: 2019 | O15: 45783.3 | P15: 45783.3 | R15: 47-52 | AC15: Association for Computing Machinery | AE15: English | AH15: Scopus | AL15: Journal Abbreviation: ACM Int. Conf. Proc. Ser. | AP15: Animation; Mixed reality; User experience; Mixed-reality environment; Speech recognition; Mapping; Wearable technology; Arts computing; Automated mapping; Botanical gardens; Intelligent virtual agents; Interaction framework; Interactive applications; Multi-Modal Interactions; Object recognition; Potential features; Speech communication; Speech interaction | BV15: ACM International Conference Proceeding Series
A16: exclude | B16: only questionnaires | C16: RPZC3DMS | D16: conferencePaper | E16: 2022 | F16: Allgaier, Mareen; Chheang, Vuthea; Saalfeld, Patrick; Apilla, Vikram; Huber, Tobias; Huettl, Florentine; Neyazi, Belal; Sandalcioglu, I. Erol; Hansen, Christian; Preim, Bernhard; Saalfeld, Sylvia | G16: A Comparison of Input Devices for Precise Interaction Tasks in VR-based Surgical Planning and Training | H16: 2022 IEEE Conference on Virtual Reality and 3D User Interfaces Abstracts and Workshops (VRW) | I16: 978-1-6654-8402-2 | K16: 10.1109/VRW55335.2022.00188 | L16: https://ieeexplore.ieee.org/document/9757571/ | N16: 2022-03 | O16: 45783.312 | P16: 45783.312 | Q16: 45783.312 | R16: 674-675 | AC16: IEEE | AD16: Christchurch, New Zealand | AF16: https://doi.org/10.15223/policy-029 | AJ16: DOI.org (Crossref) | BV16: 2022 IEEE Conference on Virtual Reality and 3D User Interfaces Abstracts and Workshops (VRW)
A17: exclude | B17: irrelevant | C17: UI3BU2NZ | D17: journalArticle | E17: 2017 | F17: Alshammari, N.; Alshammari, T.; Sedky, M.; Champion, J.; Bauer, C. | G17: OpenSHS: Open smart home simulator | H17: Sensors (Switzerland) | J17: 14248220 (ISSN) | K17: 10.3390/s17051003 | L17: https://www.scopus.com/inward/record.uri?eid=2-s2.0-85018381371&doi=10.3390%2fs17051003&partnerID=40&md5=864fbd1d76962619913c868c9cfa6f19 | M17: This paper develops a new hybrid, open-source, cross-platform 3D smart home simulator, OpenSHS, for dataset generation. OpenSHS offers an opportunity for researchers in the field of the Internet of Things (IoT) and machine learning to test and evaluate their models. Following a hybrid approach, OpenSHS combines advantages from both interactive and model-based approaches. This approach reduces the time and efforts required to generate simulated smart home datasets. We have designed a replication algorithm for extending and expanding a dataset. A small sample dataset produced, by OpenSHS, can be extended without affecting the logical order of the events. The replication provides a solution for generating large representative smart home datasets. We have built an extensible library of smart devices that facilitates the simulation of current and future smart home environments. Our tool divides the dataset generation process into three distinct phases: first design: the researcher designs the initial virtual environment by building the home, importing smart devices and creating contexts; second, simulation: the participant simulates his/her context-specific events; and third, aggregation: the researcher applies the replication algorithm to generate the final dataset. We conducted a study to assess the ease of use of our tool on the System Usability Scale (SUS). © 2017 by the authors. Licensee MDPI, Basel, Switzerland. | N17: 2017 | O17: 45783.3 | P17: 45783.3 | T17: 5 | U17: 17 | W17: Sensors | AE17: English | AH17: Scopus | AL17: Publisher: MDPI AG | AP17: Automation; Virtual reality; Visualization; Learning systems; Smart home; Smart homes; Artificial intelligence; Simulation; Intelligent buildings; Internet of things; Machine learning; Extensible library; Internet of thing (IOT); Model based approach; Replication algorithm; Smart home simulators; System Usability Scale (SUS); Visualisation
A18: exclude | B18: only questionnaires | C18: K7NG6FQP | D18: journalArticle | E18: 2024 | F18: Álvarez, Ibis M.; Manero, Borja; Romero-Hernández, Alejandro; Cárdenas, Miriela; Masó, Isabel | G18: Virtual reality platform for teacher training on classroom climate management: evaluating user acceptance | H18: Virtual Real. | J18: 1359-4338 | K18: 10.1007/s10055-024-00973-6 | L18: https://doi.org/10.1007/s10055-024-00973-6 | M18: Enhancing the educational experience through Immersive Virtual Reality (IVR) is a promising avenue, elevating the authenticity and responsiveness of simulations. Particularly in educational settings, IVR holds the potential to augment accessibility and engagement in learning. However, one pivotal aspect lies in assessing the learners' acceptance of such environments to ensure optimal and effective utilization of these technologies. This paper delves into the Didascalia Virtual-ClassRoom usability testing —an immersive IVR environment tailored for pre-service secondary school teachers. The platform transports users into a simulated classroom, where they are invited to play the role of a teacher. During the simulation, three scenarios are recreated, reproducing disruptive behaviours commonly faced in real classrooms. 84 participants (28 teachers and 56 pre-service teachers) engaged in decision-making to manage the classroom climate influenced by the simulated situations. To collect data, we used a questionnaire based on the Technology Acceptance Model (TAM) to assess and gauge users' inclinations and attitudes towards embracing the technology in question. To gain deeper insights into the user experience, participants were further invited to participate in semi-structured interviews, offering reflections and suggestions for potential enhancements. The evaluation process encompassed the perceived usefulness of the Didascalia Virtual-ClassRoom, shedding light on factors that could either facilitate or impede the adoption of this platform to enhance classroom management competence. The participants' perspectives serve as a valuable foundation for refining the tool's functionality, and their feedback fuels recommendations for its seamless integration into initial teacher training programs. | N18: 2024-03 | O18: 45783.306 | P18: 45783.306 | T18: 2 | U18: 28 | AL18: Place: Berlin, Heidelberg Publisher: Springer-Verlag | AP18: Usability evaluation; Immersive virtual reality; Classroom management; Initial teacher education; Secondary school
A19: exclude | B19: only questionnaires | C19: UCN6NLX5 | D19: conferencePaper | E19: 2022 | F19: Alvarez, Marina; Toet, Alexander; Dijkstra-Soudarissanane, Sylvie | G19: Virtual Visits: UX Evaluation of a Photorealistic AR-based Video Communication Tool | H19: Proceedings of the 1st Workshop on Interactive EXtended Reality | I19: 978-1-4503-9501-4 | K19: 10.1145/3552483.3556462 | L19: https://doi.org/10.1145/3552483.3556462 | M19: Social communication is increasingly performed through video communication (VC) tools such as Teams or Zoom. Although VC is an effective way to maintain relationships remotely, it is still limited in creating a sense of social connectedness since the interaction does not feel as natural as a physical encounter. We evaluated the user experience of a new photorealistic VC tool based on augmented reality (AR) compared with a popular VC tool (MS Teams), focusing on the feeling of social presence they provide. Participants experienced one of the systems and answered a questionnaire about their experience. In the AR condition, participants perceived a 3D image of the remote person projected in their local background (Fig.1). In the "regular video call" condition, using MS Teams, participants perceived a 2D image of the remote person in the remote background. The variables measured were social presence, interpersonal closeness, global user experience, duration of calls and perception of time, behaviour, and attitude toward the AR tool. No significant differences were found in subjective measures of social presence, interpersonal closeness, and global UX. There were also no significant differences in the duration of calls or time perception per condition. However, behavioural analysis showed that with the AR tool participants used significantly more hand gestures (non-verbal communication), showed a more relaxed attitude and laughed more frequently. Although we did not find any evidence that it provides more social presence, the AR communication tool appears to induce more natural behaviour. Both conditions received high scores on social presence and global UX. Qualitative analysis of open questions and comments showed that the human-sized image of the communication partner was the main factor driving these scores and suggested improvements for future system design. | N19: 2022 | O19: 45783.306 | P19: 45783.306 | R19: 69–75 | Y19: IXR '22 | AC19: Association for Computing Machinery | AD19: New York, NY, USA | AL19: event-place: Lisboa, Portugal | AP19: augmented reality; user experience; social connectedness; social presence; social xr; video-communication
A20: exclude | B20: only questionnaires | C20: YUQQ9FTL | D20: journalArticle | E20: 2023 | F20: Amara, K.; Kerdjidj, O.; Guerroudji, M.A.; Zenati, N.; Djekoune, O. | G20: Augmented Reality Visualization and Interaction for COVID-19 CT-Scan NN Automated Segmentation: A Validation Study | H20: IEEE Sensors Journal | J20: 1530437X (ISSN) | K20: 10.1109/JSEN.2023.3265997 | L20: https://www.scopus.com/inward/record.uri?eid=2-s2.0-85153481522&doi=10.1109%2fJSEN.2023.3265997&partnerID=40&md5=55256a5bb0b3a21152d608100598b065 | M20: Although medical imaging technology has persisted in evolving over the last decades, the techniques and technologies used for analytical and visualization purposes have remained constant. Manual or semiautomatic segmentation is, in many cases, complicated. It requires the intervention of a specialist and is time-consuming, especially during the coronavirus disease (COVID-19) pandemic, which has had devastating medical and economic consequences. Processing and visualizing medical images with advanced techniques represent medical professionals' breakthroughs. This article studies how augmented reality (AR) and artificial intelligence (AI) can transform medical practice during COVID-19 and post-COVID-19 pandemic. Here, we report an AR visualization and interaction platform; it covers the whole process from uploading chest computed tomography (CT)-scan images to automatic segmentation-based deep learning, 3-D reconstruction, 3-D visualization, and manipulation. AR provides a more realistic 3-D visualization system, allowing doctors to effectively interact with the generated 3-D model of segmented lungs and COVID-19 lesions. We use the U-Net neural network (NN) for automated segmentation. The statistical measures obtained using the Dice score, pixel accuracy, sensitivity, G -mean, and specificity are 0.749, 0.949, 0.956, 0.955, and 0.954, respectively. The user-friendliness and usability are objectified by a formal user study that compared our AR-assisted design to the standard diagnosis setup. One hundred and six doctors and medical students, including eight senior medical lecturers, volunteered to assess our platform. The platform could be used as an aid-diagnosis tool to identify and analyze the COVID-19 infectious or as a training tool for residents and medical students. The prototype can be extended to other pulmonary pathologies. © 2001-2012 IEEE. | N20: 2023 | O20: 45783.3 | P20: 45783.3 | R20: 12114-12123 | T20: 11 | U20: 23 | W20: IEEE Sensors J. | AE20: English | AH20: Scopus | AL20: Publisher: Institute of Electrical and Electronics Engineers Inc. | AP20: Diagnosis; Automation; Augmented reality; Reality visualization; 3D modeling; Three dimensional computer graphics; Visualization; deep learning; Deep learning; Computerized tomography; Image segmentation; Neural-networks; Medical imaging; AR interaction; AR visualization; augmented reality (AR); Augmented reality interaction; Augmented reality visualization; automated segmentation; Automated segmentation; coronavirus disease (COVID-19); COVID-19; CT-scan; medical imaging; Medical students; U-net; U-Net; Validation study
A21: exclude | B21: only questionnaires | C21: Z3VZPTHV | D21: journalArticle | E21: 2023 | F21: Anderies; Marvella, Maevy; Hakim, Nissa Adila; Seciawanto, Priskilla Adriani; Chowanda, Andry | G21: Implementation of Augmented Reality in Android-based Application to Promote Indonesian Tourism | H21: Procedia Comput. Sci. | J21: 1877-0509 | K21: 10.1016/j.procs.2023.10.560 | L21: https://doi.org/10.1016/j.procs.2023.10.560 | N21: 2023-01 | O21: 45783.306 | P21: 45783.306 | R21: 573–581 | T21: C | U21: 227 | AL21: Place: NLD Publisher: Elsevier Science Publishers B. V. | AP21: Augmented Reality; Usability Testing; Android; Indonesian Tourism
A22: exclude | B22: irrelevant | C22: M9V853HD | D22: conferencePaper | E22: 2020 | F22: Anderson, Sarah E. | G22: Virtual Reality for Safety and Independence in Everyday Activities | H22: 2020 IEEE Conference on Virtual Reality and 3D User Interfaces Abstracts and Workshops (VRW) | I22: 978-1-7281-6532-5 | K22: 10.1109/VRW50115.2020.00118 | L22: https://ieeexplore.ieee.org/document/9090475/ | N22: 2020-03 | O22: 45783.311 | P22: 45783.311 | Q22: 45783.311 | R22: 533-534 | AC22: IEEE | AD22: Atlanta, GA, USA | AF22: https://ieeexplore.ieee.org/Xplorehelp/downloads/license-information/IEEE.html | AJ22: DOI.org (Crossref) | BV22: 2020 IEEE Conference on Virtual Reality and 3D User Interfaces Abstracts and Workshops (VRW)
A23: exclude | B23: only questionnaires | C23: 3XMX9UPU | D23: conferencePaper | E23: 2019 | F23: Andri, C.; Alkawaz, M.H.; Waheed, S.R. | G23: Examining Effectiveness and User Experiences in 3D Mobile based Augmented Reality for MSU Virtual Tour | H23: IEEE Int. Conf. Autom. Control Intell. Syst., I2CACIS - Proc. | I23: 978-172810784-4 (ISBN) | K23: 10.1109/I2CACIS.2019.8825054 | L23: https://www.scopus.com/inward/record.uri?eid=2-s2.0-85072923510&doi=10.1109%2fI2CACIS.2019.8825054&partnerID=40&md5=4acf3b96b28372ad9681568c2f56e19a | M23: A campus tour is a time-consuming event and human resource intensive task. It is not always possible for visitors to visit all the facilities on a one-day tour due to the time limit or some activities on campus that cannot be disturbed. Along with technological advancements, some universities began to use multimedia technology as a supporting media for campus tour activities. This paper presents the mobile augmented reality and virtual tour application for Management and Science University (MSU). This application will able to help visitors in the process of obtaining such information on MSU in a very simple way by augmented reality feature, and let the visitors become familiar with MSU's environment by virtual tour feature. This project also presents the main use cases covered by the application and describes the main feature components. Furthermore, the evaluation of the application based on user testing is also explained. © 2019 IEEE. | N23: 2019 | O23: 45783.3 | P23: 45783.3 | R23: 161-167 | AC23: Institute of Electrical and Electronics Engineers Inc. | AE23: English | AH23: Scopus | AL23: Journal Abbreviation: IEEE Int. Conf. Autom. Control Intell. Syst., I2CACIS - Proc. | AP23: Mobile applications; Automation; augmented reality; Augmented reality; 3D modeling; 3D models; Three dimensional computer graphics; User experience; Technological advancement; Intelligent systems; Multimedia systems; mobile application; Mobile augmented reality; User testing; campus tour; Multimedia technologies; Process control; virtual tour; Virtual tour | BV23: 2019 IEEE International Conference on Automatic Control and Intelligent Systems, I2CACIS 2019 - Proceedings
A24: for-fulltext | B24: multimodal ux NN | C24: ID2E66RY | D24: journalArticle | E24: 2025 | F24: Pannattee, Peerawat; Shimada, Shogo; Yem, Vibol; Nishiuchi, Nobuyuki | G24: A deep learning framework for automatic assessment of presence in virtual reality using multimodal behavioral cues | H24: Neural Comput. Appl. | J24: 0941-0643 | K24: 10.1007/s00521-024-10943-3 | L24: https://doi.org/10.1007/s00521-024-10943-3 | M24: Effective development of virtual reality (VR) applications is heavily reliant on the evaluation of user experience (UX). However, traditional methods such as questionnaires have inherent limitations which hinder their ability to capture nuanced behavioral responses and impede the agility of VR content creation: They are time-consuming, burdensome for users, and require significant human effort for interpretation. This study introduces an automated framework aimed at addressing the limitations of questionnaire-based evaluations to assess UX in VR. Our primary focus is to validate the concept of this framework through assessment of the sense of presence (SOP), a crucial psychological perception with significant impact on VR UX. Our proposed framework utilizes a deep neural network (DNN) to analyze patterns in multimodal behavioral cues, including facial expressions, head movements, and hand movements, to predict scores from the Igroup Presence Questionnaire (IPQ). Additionally, we introduce two statistical profiles: the Visual Entropy Profile (VEP), which offers insights into visual complexity by depicting scene entropy, and the Experiential Presence Profile (EPP), which is designed to capture users’ historical SOP levels to enable personalized baseline and sensitivity estimation. The proposed framework achieves a significant correlation between actual and predicted IPQ scores, with a Spearman’s rank correlation coefficient of 0.7303, showcasing the potential of DNNs in analyzing complex behavioral signals and automating SOP assessment. This study represents a pioneering effort in leveraging DNNs for the automatic assessment of SOP and paves the way for future advances in automatically assessing VR UX and unlocking new opportunities in the field. | N24: 2025-01 | O24: 45783.306 | P24: 45783.376 | R24: 6283–6303 | T24: 8 | U24: 37 | AL24: Place: Berlin, Heidelberg Publisher: Springer-Verlag | AP24: Virtual environments; Virtual reality; Virtualization; Users' experiences; Deep learning; Deep neural networks; Automatic assessment; Behavioral cues; Behavioral response; Contrastive Learning; Economic and social effects; Evaluation of users; Inherent limitations; Learning frameworks; Multi-modal; Sense of presence; Sense of presences; User experience
A25: exclude | B25: only questionnaires | C25: RD76TVS3 | D25: conferencePaper | E25: 2024 | F25: Anggraini, Lisa; Santoso, Meilinda; Sunardi | G25: UX Analysis of Augmented Reality in E-Commerce Marketing Using the System Usability Scale and Usability Testing Method | H25: 2024 10th International HCI and UX Conference in Indonesia (CHIuXiD) | I25: 979-8-3503-8043-9 | K25: 10.1109/CHIuXiD64022.2024.10860502 | L25: https://ieeexplore.ieee.org/document/10860502/ | N25: 45611 | O25: 45783.311 | P25: 45783.311 | Q25: 45783.311 | R25: 72-77 | AC25: IEEE | AD25: Jakarta, Indonesia | AF25: https://doi.org/10.15223/policy-029 | AJ25: DOI.org (Crossref) | BV25: 2024 10th International HCI and UX Conference in Indonesia (CHIuXiD)
A26: for-fulltext | B26: physiological factors | C26: M9YJKLGD | D26: journalArticle | E26: 2016 | F26: Bian, Yulong; Yang, Chenglei; Gao, Fengqiang; Li, Huiyu; Zhou, Shisheng; Li, Hanchao; Sun, Xiaowen; Meng, Xiangxu | G26: A framework for physiological indicators of flow in VR games: construction and preliminary evaluation | H26: Personal Ubiquitous Comput. | J26: 1617-4909 | K26: 10.1007/s00779-016-0953-5 | L26: https://doi.org/10.1007/s00779-016-0953-5 | M26: Flow experience is often considered as an important standard of ideal user experience (UX). Till now, flow is mainly measured via self-report questionnaires, which cannot evaluate flow immediately and objectively. In this paper, we constructed a physiological evaluation model to evaluate flow in virtual reality (VR) game. The evaluation model consists of five first-level indicators and their respective second-level indicators. Then, we conducted an empirical experiment to test the effectiveness of partial indicators to predict flow experience. Most results supported the model and revealed that heart rate, interbeat interval, heart rate variability (HRV), low-frequency HRV (LF-HRV), high-frequency HRV (HF-HRV), and respiratory rate are all effective indicators in predicting flow experience. Further research should be conducted to improve the evaluation model and conclude practical implications in UX and VR game design. | N26: 2016-10 | O26: 45783.306 | P26: 45783.306 | R26: 821–832 | T26: 5 | U26: 20 | AL26: Place: Berlin, Heidelberg Publisher: Springer-Verlag | AP26: User experience; Flow experience; Physiological evaluation model; Virtual reality game
A27: exclude | B27: only questionnaires | C27: 23XJEEV4 | D27: conferencePaper | E27: 2022 | F27: Apraiz Iriarte, A.; Lasa Erle, G.; Serrano Muñoz, A.; Elguea Aguinaco, Í.; Arana Arexolaleiba, N. | G27: EVALUATION OF THE USER EXPERIENCE OF AN INDUSTRIAL ROBOTIC ENVIRONMENT IN VIRTUAL REALITY | H27: Proc. Int. Congr. Proj. Manag. Eng. | I27: 26955067 (ISSN); 978-840944521-9 (ISBN) | L27: https://www.scopus.com/inward/record.uri?eid=2-s2.0-85150344654&partnerID=40&md5=386cef55407747a7c1cc769e6e219485 | M27: Industry 4.0 is leading to a whole new level of process automation, thus redefining the role of humans, and altering existing jobs in yet unknown ways. Although the number of robots in the manufacturing industry has been steadily increasing for several decades, the current growth trend is remarkable given the number and variety of industries using robots. Operators need to have positive and fit-for-purpose experiences through trust-based, smooth, safe, and satisfying interaction to integrate robots as a natural part of their daily lives. In this sense, virtual reality is presented as an optimal technology to evaluate this interaction while ensuring safe conditions, but the impact it has on human factors still has unknowns to be solved. This research paper presents an evaluation study of the human factors resulting from collaboration with an industrial robot in a virtual environment taking into account the gender perspective. For this purpose, the behaviour of the users (n=8) has been analysed and the interaction has been evaluated by means of two questionnaires to correlate task performance and subjective perception. © 2022 by the authors. Licensee AEIPRO, Spain. This article is licensed under a Creative Commons Attribution-NonCommercial-NoDerivatives 4.0 International License (https://creativecommons.org/licenses/by-ncnd/4.0/) | N27: 2022 | O27: 45783.3 | P27: 45783.3 | R27: 1686-1698 | U27: 2022-July | X27: EVALUACIÓN DE LA EXPERIENCIA DE USO DE UN ENTORNO ROBÓTICO INDUSTRIAL EN REALIDAD VIRTUAL | AC27: Asociacion Espanola de Direccion e Ingenieria de Proyectos (AEIPRO) | AE27: Spanish | AH27: Scopus | AL27: Journal Abbreviation: Proc. Int. Congr. Proj. Manag. Eng. | AP27: Human Factors; Human-Robot Interaction (HRI); Interaction; User eXperience (UX); Virtual Reality (VR) | BV27: Proceedings from the International Congress on Project Management and Engineering
A28: exclude | B28: only questionnaires | C28: L2DXFNY6 | D28: journalArticle | E28: 2023 | F28: Ariano, R.; Manca, M.; Paternò, F.; Santoro, C. | G28: Smartphone-based augmented reality for end-user creation of home automations | H28: Behaviour and Information Technology | J28: 0144929X (ISSN) | K28: 10.1080/0144929X.2021.2017482 | L28: https://www.scopus.com/inward/record.uri?eid=2-s2.0-85122650527&doi=10.1080%2f0144929X.2021.2017482&partnerID=40&md5=f135cc2aee5c551306d803cd45074788 | M28: In the last few years, several end-user tools have been designed to help people who are not professional developers in programming their smart environments. However, such tools are often based on structured visual editors providing abstract representations of the available connected sensors and objects, which can be problematic for end users, and do not particularly encourage their participation. This work aims to make the end-user experience of creating everyday automations involving various types of connected sensors and objects more engaging by replacing extensive, static, structured and comprehensive abstract visual tools with more narrowed, relevant, context-sensitive, dynamic, augmented reality-based representations. We present a solution for this purpose that mobile users can exploit through their smartphone. End users can use the smartphone camera to frame the relevant sensor or object through the developed prototype, then get the current automations associated with it, edit their definition, create new ones as well as monitor the automations involving the whole current environment. We also report a first user test of the developed prototype deployed in a home equipped with connected sensors and objects, which yielded positive feedback. © 2022 Informa UK Limited, trading as Taylor & Francis Group. | N28: 2023 | O28: 45783.3 | P28: 45783.3 | R28: 124-140 | T28: 1 | U28: 42 | W28: Behav Inf Technol | AE28: English | AH28: Scopus | AL28: Publisher: Taylor and Francis Ltd. | AP28: Smart phones; Automation; Augmented reality; User interfaces; 'current; Smart homes; Feedback; Abstract representation; End-user development; End-User Development; End-users; everyday automation; Everyday automation; Home automation; Smart environment; smart home; Smartphones; Visual editors
A29: exclude | B29: irrelevant | C29: M5QUWAWH | D29: journalArticle | E29: 2016 | F29: Arroyo, I.; Giné, F.; Roig, C.; Granollers, T. | G29: Analyzing Google Earth application in a heterogeneous commodity cluster display wall | H29: Multimedia Tools and Applications | J29: 13807501 (ISSN) | K29: 10.1007/s11042-015-2859-z | L29: https://www.scopus.com/inward/record.uri?eid=2-s2.0-84940399006&doi=10.1007%2fs11042-015-2859-z&partnerID=40&md5=15a9c7d40f857984aa1e041675ce8d85 | M29: Nowadays, clusters of interconnected workstations have become a common solution for powering large composite displays, or “cluster display walls”, to visualize high resolution images. Our paper is focused on analyzing a specific cluster display wall developed by Google, named Liquid Galaxy, made up of heterogeneous commodity hardware with different degrees of heterogeneity, running master-slave (Google Earth) and client-server (Quake III Arena) multimedia applications. With this in mind, we define and test different scenarios, representing the behavior of many kinds of users. Our results show that the CPU, memory and network are good enough to execute the client-server application, while, depending on the user behavior, the external network constitutes the bottleneck of the system in Google Earth. So, the master-slave application has focused our attention. Likewise, in order to analyze the users’ point of view when interacting with Google Earth in the Liquid Galaxy, we define a new metric, named Visualization Rate (VR), which enables a relationship to be established between the user experience and the platform performance. In order to set the minimum acceptable value of the VR parameter according to users perception, we carried out different tests with real users. Then, this minimum threshold was compared with the VR value obtained from the automated benchmarking performed afterwards on clusters with different heterogeneity degrees. Finally, we analyzed the VR trend when the Liquid Galaxy is scaled from 3 up to 8 nodes in both the homogeneous and heterogeneous architectures to study the scalability of the system. © 2015, The Author(s). | N29: 2016 | O29: 45783.3 | P29: 45783.392 | R29: 11391-11416 | T29: 18 | U29: 75 | W29: Multimedia Tools Appl | AE29: English | AH29: Scopus | AL29: Publisher: Springer New York LLC | AP29: Behavioral research; Benchmarking; Client server; Client-server; Client-server applications; Cluster display wall; Galaxies; Google Earth; Google earths; Heterogeneous architectures; Liquid galaxy; Liquids; Master slave; Master-slave; Master-slave application; Multimedia applications
A30: exclude | B30: only questionnaires | C30: HSZMACV2 | D30: conferencePaper | E30: 2023 | F30: Asghar, Ikram; Ullah, Rahmat; Griffiths, Mark G; Warren, William; Dando, Luke; Davies, John | G30: A User-Centered System Usability Evaluation of a Virtual Reality Application Developed for Solar Farm Training | H30: Proceedings of the 2023 9th International Conference on Computer Technology Applications | I30: 978-1-4503-9957-9 | K30: 10.1145/3605423.3605456 | L30: https://doi.org/10.1145/3605423.3605456 | M30: The hazardous potential of the Photovoltaic (PV) industry demands the most rigorous and professional training. However, such training requires many resources and time and has potential health and safety risks. Incorporating emerging technologies in such training can be helpful. This paper proposes SolarPro, a virtual reality application for solar farm training that can aid solar farm trainees in getting initial training in the virtual environment. The application's usability is tested through multiple testing sessions with 30 participants. The testing participants experienced the virtual scenarios, completed the tasks and filled out the system usability questionnaires. The system usability scale analysis resulted in a grade A score of 81.75. The analysis based on the demographic characteristics also showed positive results. We can conclude that the SolarPro virtual reality application has high system usability. However, it is suggested to have more than just 30 respondents for the usability test to conclude more promising results.CCS CONCEPTS • Human-centered computing ∼Human computer interaction (HCI) ∼Interaction paradigms ∼Virtual reality | N30: 2023 | O30: 45783.306 | P30: 45783.306 | R30: 157–165 | Y30: ICCTA '23 | AC30: Association for Computing Machinery | AD30: New York, NY, USA | AL30: event-place: Vienna, Austria | AP30: Virtual reality; System usability; User testing; Solar farm
A31: exclude | B31: only questionnaires | C31: 5QU5RXJZ | D31: journalArticle | E31: 2022 | F31: Avan, Emre; Capin, Tolga K.; Gurcay, Hasmet; Celikcan, Ufuk | G31: Enhancing VR experience with RBF interpolation based dynamic tuning of stereoscopic rendering | H31: Comput. Graph. | J31: 0097-8493 | K31: 10.1016/j.cag.2021.09.016 | L31: https://doi.org/10.1016/j.cag.2021.09.016 | N31: 2022-02 | O31: 45783.306 | P31: 45783.306 | R31: 390–401 | T31: C | U31: 102 | AL31: Place: USA Publisher: Pergamon Press, Inc. | AP31: Virtual reality; Depth authoring; Depth perception; RBF interpolation; Stereoscopic rendering
A32: exclude | B32: only questionnaires | C32: TF2NUSK9 | D32: journalArticle | E32: 2020 | F32: Bacchin, D.; Pluchino, P.; Furlan, M.; Minen, M.; Minen, D.; Formaggia, F.; Bruschetta, M.; Beghi, A.; Gamberini, L. | G32: Subjective evaluation of autonomous and manual driving in advanced simulation | H32: Annual Review of CyberTherapy and Telemedicine | J32: 15548716 (ISSN) | L32: https://www.scopus.com/inward/record.uri?eid=2-s2.0-85115747548&partnerID=40&md5=33ff07913c01569c82082d0c5f35d1ba | M32: In the present study, we compare the user experience of driving a fully automated vehicle with that of driving a fully manual vehicle. We used a high-fidelity simulator displaying a highway road with four different obstacles. The user experience and usability of 26 participants was compared in the two conditions. The sense of presence in the simulation was also measured. The results showed differences between the two conditions. © 2020, Interactive Media Institute. All rights reserved. | N32: 2020 | O32: 45783.3 | P32: 45783.3 | R32: 81-85 | U32: 18 | W32: Annu. Rev. Cyber Ther. Telemedicine | AE32: English | AH32: Scopus | AL32: Publisher: Interactive Media Institute | AP32: usability; virtual reality; Virtual Reality; Article; controlled study; human; adult; female; male; simulation; priority journal; Autonomous Driving; car driving; human computer interaction; Human-computer Interactions
A33: exclude | B33: literature review | C33: NFYLUBG4 | D33: journalArticle | E33: 2012 | F33: Bai, Zhen; Blackwell, Alan F. | G33: Analytic review of usability evaluation in ISMAR | H33: Interacting with Computers | J33: 9535438 | K33: 10.1016/j.intcom.2012.07.004 | L33: https://academic.oup.com/iwc/article-lookup/doi/10.1016/j.intcom.2012.07.004 | N33: 2012-11 | O33: 45783.306 | P33: 45783.392 | Q33: 45783.311 | R33: 450-460 | T33: 6 | U33: 24 | W33: Interacting with Computers | AE33: en | AJ33: DOI.org (Crossref) | AP33: Augmented Reality; Usability evaluation; User experience; Collaboration
A34: exclude | B34: irrelevant | C34: 92J83N9M | D34: journalArticle | E34: 2010 | F34: Baillie, S.; Crossan, A.; Brewster, S.A.; May, S.A.; Mellor, D.J. | G34: Evaluating an automated haptic simulator designed for veterinary students to learn bovine rectal palpation | H34: Simulation in Healthcare | J34: 1559713X (ISSN) | K34: 10.1097/SIH.0b013e3181e369bf | L34: https://www.scopus.com/inward/record.uri?eid=2-s2.0-78049290337&doi=10.1097%2fSIH.0b013e3181e369bf&partnerID=40&md5=0a7dce1df967f77e9127ebfdfb4b7134 | M34: INTRODUCTION:: Simulators provide a potential solution to some of the challenges faced when teaching internal examinations to medical or veterinary students. A virtual reality simulator, the Haptic Cow, has been developed to teach bovine rectal palpation to veterinary students, and significant training benefits have been demonstrated. However, the training needs to be delivered by an instructor, a requirement that limits availability. This article describes the development and evaluation of an automated version that students could use on their own. METHODS:: An automated version was developed based on a recording of an expert's examination. The performance of two groups of eight students was compared. All students had undergone the traditional training in the course, namely lectures and laboratory practicals, and then group S used the simulator whereas group R had no additional training. The students were set the task of finding the uterus when examining cows. The simulator was then made available to students, and feedback about the "usability" was gathered with a questionnaire. RESULTS:: The group whose training had been supplemented with a simulator session were significantly better at finding the uterus. The questionnaire feedback was positive and indicated that students found the simulator easy to use. CONCLUSIONS:: The automated simulator equipped students with useful skills for examining cows. In addition, a simulator that does not need the presence of an instructor will increase the availability of training for students and be a more sustainable option for institutions. Copyright © 2010 Society for Simulation in Healthcare. | N34: 2010 | O34: 45783.3 | P34: 45783.3 | R34: 261-266 | T34: 5 | U34: 5 | W34: Simul. Healthc. | AE34: English | AH34: Scopus | AP34: Humans; human; Virtual reality; Teaching; article; questionnaire; Software; education; Educational Measurement; Validation; teaching; Training; animal; Animals; Questionnaires; computer simulation; Computer Simulation; methodology; computer program; animal model; cattle; Cattle; digital rectal examination; Digital Rectal Examination; educational status; Educational Status; England; Haptic; London; Models, Animal; Palpation; rectum; Rectum; school; Schools, Veterinary; Simulator; United Kingdom; Veterinary; veterinary medicine; Veterinary Medicine
A35: for-fulltext | B35: automation unclear, read fulltext | C35: XYVJ5GV5 | D35: journalArticle | E35: 2008 | F35: Seffah, Ahmed; Benn, Jonathan; Mammar, Halima Habieb | G35: A low-cost test environment for usability studies of head-mounted virtual reality systems | H35: J. Usability Studies | M35: There is a need to develop new usability testing environments and methodologies for unconventional interactive systems. Pursuant to that need, we developed a low-cost test environment for a Head-Mounted Display (HMD)-based, virtual reality system called Osmose. Osmose was difficult to test for many reasons, one of which was its style of interaction. We began setting up the testing environment about two weeks before the start of the usability testing. We learned many lessons throughout the experience. This paper summarizes the study findings, both methodological – how to setup and conduct a usability lab for such an environment – as well as conceptual –the human experiences and behavioral patterns involved in using an immersive environment. | N35: 2008-02 | O35: 45783.306 | P35: 45783.306 | R35: 60–73 | T35: 2 | U35: 3 | AL35: Place: Bloomingdale, IL Publisher: Usability Professionals' Association | AP35: virtual reality; usability testing; breathing interaction; head-mounted display; immersive systems; sensing-based interaction
A36: exclude | B36: only questionnaires | C36: PPQ47G4I | D36: conferencePaper | E36: 2024 | F36: Baldeón, Johan; Auccapuri, Darwin; Díaz, Emilio; Masuda, Andrés; Gálvez, Rodolfo | G36: Evaluating the Effectiveness of an Augmented Reality Platform in Promoting Sustainable Tourism in the Peruvian Amazon Jungle | H36: HCI International 2024 – Late Breaking Papers: 26th International Conference on Human-Computer Interaction, HCII 2024, Washington, DC, USA, June 29 – July 4, 2024, Proceedings, Part V | I36: 978-3-031-76814-9 | K36: 10.1007/978-3-031-76815-6_16 | L36: https://doi.org/10.1007/978-3-031-76815-6_16 | M36: This work explores the potential of Augmented Reality (AR) to boost the sustainability of tourist experiences in the Peruvian Amazon, leveraging a comprehensive UX evaluation of the “Pacaya Samiria” AR platform. Motivated by the increasing role of technology in tourism, we delve into the multifaceted impact of AR on visitor behavior and environmental stewardship. The meticulously designed “Pacaya Samiria” AR platform immerses visitors in the Amazon’s biodiversity and cultural heritage while promoting eco-awareness. Employing advanced methodologies and UX expertise, we conducted a rigorous evaluation using focus groups and the User Experience Questionnaire (UEQ). This allowed us to assess the platform’s strengths (immersion, education), weaknesses (technical challenges, cultural relevance), and overall impact on visitor perceptions and behaviors. Key findings highlight the crucial role of context-sensitive design and content curation for effective AR implementation in remote ecotourism settings. While “Pacaya Samiria" demonstrates promise, opportunities for optimization exist, particularly in addressing technical limitations and enhancing cultural integration. This research contributes to Sustainable HCI by offering actionable insights into how AR can support environmental conservation and enrich visitor experiences in ecotourism destinations. By unveiling the intricate dynamics of UX in the Amazon, we inform future initiatives harnessing technology for global sustainable tourism development. | N36: 2024 | O36: 45783.306 | P36: 45783.306 | R36: 223–241 | AC36: Springer-Verlag | AD36: Berlin, Heidelberg | AL36: event-place: Washington DC, USA | AP36: augmented reality; User experience; Amazon jungle; cultural sensitivity; focus group method; sustainable tourism; UX evaluation
A37: exclude | B37: irrelevant | C37: 445HQGGN | D37: conferencePaper | E37: 2020 | F37: Barz, A.; Conrad, J.; Wallach, D. | G37: Advantages of Using Runtime Procedural Generation of Virtual Environments Based on Real World Data for Conducting Empirical Automotive Research | H37: Lect. Notes Comput. Sci. | I37: 03029743 (ISSN); 978-303059986-7 (ISBN) | K37: 10.1007/978-3-030-59987-4_2 | L37: https://www.scopus.com/inward/record.uri?eid=2-s2.0-85090500610&doi=10.1007%2f978-3-030-59987-4_2&partnerID=40&md5=11b0e469e68ed895cbe4a67884947327 | M37: Driving simulations have become important research tools for improving the in-car user experience. Simulations are especially indispensable when conducting empirical studies in a human-centered development process, where iterative testing in real-world environments is very time-consuming, expensive and potentially dangerous. Constantly advancing possibilities offered by new generations of driving simulations increase the demands and expectations of simulation systems. While the implementation of many components such as simulation hardware or driving physics is very mature by now, the realization of virtual driving environments and scenarios is still a challenging endeavor. A partially automated, algorithmic generation of virtual environments based on real world data provides a possible solution to simplify set-up and execution of research scenarios. The data formats used for this purpose are digital elevation models and map data that can be iteratively processed, improved and expanded for the use in a concrete study. This approach usually requires additional manual steps after the procedural generation is completed. This paper outlines an automated, algorithmic generation of virtual environments based on real-world data, realized at runtime and without subsequent manual post-processing. Significant benefits in automotive research enabled by this approach such as rapid prototyping of study scenarios, support for large-scale virtual environments and the analysis of driving behavior in familiar environments are described. © 2020, Springer Nature Switzerland AG. | N37: 2020 | O37: 45783.3 | P37: 45783.3 | R37: 14-23 | U37: 12429 LNCS | AC37: Springer Science and Business Media Deutschland GmbH | AE37: English | AH37: Scopus | AL37: Journal Abbreviation: Lect. Notes Comput. Sci. | AP37: Digital elevation model; VR; Automobile drivers; User experience; Ergonomics; Iterative methods; Driving simulation; Human computer interaction; Development process; Analysis of driving behavior; Automotive research; Driving environment; Large-scale virtual environment; OpenDRIVE; OpenStreetMap; Real world environments; Simulation systems | AR37: Stephanidis C.; Duffy V.G.; Streitz N.; Konomi S.; Krömker H. | BV37: Lecture Notes in Computer Science (including subseries Lecture Notes in Artificial Intelligence and Lecture Notes in Bioinformatics)
A38: exclude | B38: no automation | C38: IRZAK4WD | D38: conferencePaper | E38: 2021 | F38: Bastos, Arthur; Pinto, Alano; Ribeiro, Samira; Ferreira, Leonardo; Reis, Flavio; Chayel, Murilo | G38: Copelia: Wearable Augmented Reality Application for Training and Maintenance of Reclosers | H38: 12th Augmented Human International Conference | I38: 978-1-4503-9030-9 | K38: 10.1145/3460881.3460926 | L38: https://doi.org/10.1145/3460881.3460926 | M38: This short paper describes the study case of Copelia, an on-going project for a major Brazilian electricity company. The application employs augmented reality for training and maintenance. It runs on an HMT-1 smart glass and features automatic detection of reclosers and guided instructions for maintenance operations. This allows generalist electricians to perform tasks that would otherwise be performed exclusively by other skilled professionals. Preliminary results show that Copelia’s features are desirable for this kind of application and they can indeed be useful for both maintenance and training. However, users are not familiar with the technology and resisted the voice control interaction paradigm. The team identified problems related to functionality and user experience which may apply to similar applications. Future works include user testing to assess whether the improvements to the user interface reflect in a broader acceptance of the application. | N38: 2021 | O38: 45783.306 | P38: 45783.411 | Y38: AH2021 | AC38: Association for Computing Machinery | AD38: New York, NY, USA | AL38: event-place: Geneva, Switzerland | AP38: Augmented Reality; Augmented reality; User interfaces; Acceptance tests; User experience; Voice control; Augmented reality applications; Maintenance; Automatic Detection; Interaction paradigm; Automatic guided vehicles; Electric power generation; Electricity companies; Maintenance operations; Smart glass; Training; User testing; Wearable computers
A39: exclude | B39: only questionnaires | C39: 9ACH485M | D39: conferencePaper | E39: 2024 | F39: Basumatary, Dipali; Das, Debojeet; Chakraborty, Swaubhik; Biswas, Sourav Kumar; Maity, Ranjan | G39: Development and Testing of ‘TeachAR’ – A Web-Based Augmented Reality Teaching Platform | H39: 2024 2nd World Conference on Communication &amp; Computing (WCONF) | I39: 979-8-3503-9532-7 | K39: 10.1109/WCONF61366.2024.10692207 | L39: https://ieeexplore.ieee.org/document/10692207/ | N39: 45485 | O39: 45783.312 | P39: 45783.452 | Q39: 45783.312 | R39: 45839 | AC39: IEEE | AD39: RAIPUR, India | AF39: https://doi.org/10.15223/policy-029 | AJ39: DOI.org (Crossref) | AP39: Web applications; Usability engineering; augmented reality; Augmented reality; usability testing; 3D modeling; Students; Teaching; E-learning; WEB application; Usability testing; Development and testing; E - learning; e-learning; education; Federated learning; Teachers'; Teaching and learning; Teaching platform; Web-based augmented realities; WebAR | BV39: 2024 2nd World Conference on Communication &amp; Computing (WCONF)
A40: exclude | B40: only questionnaires | C40: VQDGATDN | D40: journalArticle | E40: 2023 | F40: Battegazzorre, Edoardo; Strada, Francesco; De Francesco, Lucia; Mazza, Alessandro; Monte, Olga Dal; Bottino, Andrea | G40: Influencer-Based Virtual Reality Stroop Task | H40: IEEE Access | J40: 2169-3536 | K40: 10.1109/ACCESS.2023.3324554 | L40: https://ieeexplore.ieee.org/document/10285114/ | N40: 2023 | O40: 45783.313 | P40: 45783.313 | Q40: 45783.313 | R40: 126420-126435 | U40: 11 | W40: IEEE Access | AF40: https://creativecommons.org/licenses/by/4.0/legalcode | AJ40: DOI.org (Crossref) | AN40: /Users/dennis/Zotero/storage/NK3RL2NE/Battegazzorre et al. - 2023 - Influencer-Based Virtual Reality Stroop Task.pdf
A41: exclude | B41: only questionnaires | C41: 9ZQN9KV7 | D41: bookSection | E41: 2022 | F41: Bauer, Valentin; Bouchara, Tifanie; Duris, Olivier; Labossière, Charlotte; Clément, Marie-Noëlle; Bourdot, Patrick | G41: Evaluating the Acceptability and Usability of a Head-Mounted Augmented Reality Approach for Autistic Children with High Support Needs | H41: Virtual Reality and Mixed Reality | I41: 978-3-031-16233-6 978-3-031-16234-3 | L41: https://link.springer.com/10.1007/978-3-031-16234-3_4 | N41: 2022 | O41: 45783.293 | P41: 45783.293 | Q41: 45783.293 | R41: 53-72 | U41: 13484 | AC41: Springer International Publishing | AD41: Cham | AE41: en | AJ41: DOI.org (Crossref) | AL41: Series Title: Lecture Notes in Computer Science DOI: 10.1007/978-3-031-16234-3_4 | AN41: /Users/dennis/Zotero/storage/PAYZD2LM/Bauer et al. - 2022 - Evaluating the Acceptability and Usability of a Head-Mounted Augmented Reality Approach for Autistic.pdf | AR41: Zachmann, Gabriel; Alcañiz Raya, Mariano; Bourdot, Patrick; Marchal, Maud; Stefanucci, Jeanine; Yang, Xubo
A42: exclude | B42: only interviews | C42: ZAFZ2K23 | D42: conferencePaper | E42: 2020 | F42: Baum, David; Bechert, Stefan; Eisenecker, Ulrich; Meichsner, Isabelle; Muller, Richard | G42: Identifying Usability Issues of Software Analytics Applications in Immersive Augmented Reality | H42: 2020 Working Conference on Software Visualization (VISSOFT) | I42: 978-1-7281-9914-6 | K42: 10.1109/VISSOFT51673.2020.00015 | L42: https://ieeexplore.ieee.org/document/9240485/ | N42: 2020-09 | O42: 45783.312 | P42: 45783.312 | Q42: 45783.312 | R42: 100-104 | AC42: IEEE | AD42: Adelaide, Australia | AF42: https://ieeexplore.ieee.org/Xplorehelp/downloads/license-information/IEEE.html | AJ42: DOI.org (Crossref) | AN42: /Users/dennis/Zotero/storage/IAU9HQGH/Baum et al. - 2020 - Identifying Usability Issues of Software Analytics Applications in Immersive Augmented Reality.pdf | BV42: 2020 Working Conference on Software Visualization (VISSOFT)
A43: exclude | B43: only questionnaires | C43: M8XISAGR | D43: journalArticle | E43: 2024 | F43: Bazargani, J.S.; Rahim, N.; Sadeghi-Niaraki, A.; Abuhmed, T.; Song, H.; Choi, S.-M. | G43: Alzheimer's disease diagnosis in the metaverse | H43: Computer Methods and Programs in Biomedicine | J43: 01692607 (ISSN) | K43: 10.1016/j.cmpb.2024.108348 | L43: https://www.scopus.com/inward/record.uri?eid=2-s2.0-85199518500&doi=10.1016%2fj.cmpb.2024.108348&partnerID=40&md5=7cfdfbdd6f0e475f0e8a52d5219d3667 | M43: Background and Objective: The importance of early diagnosis of Alzheimer's Disease (AD) is by no means negligible because no cure has been recognized for it rather than some therapies only lowering the pace of progression. The research gap reveals information on the lack of an automatic non-invasive approach toward the diagnosis of AD, in particular with the help of Virtual Reality (VR) and Artificial Intelligence. Another perspective highlights that current VR studies fail to incorporate a comprehensive range of cognitive tests and consider design notes for elderlies, leading to unreliable results. Methods: This paper tried to design a VR environment suitable for older adults in which three cognitive assessments namely: ADAS-Cog, Montreal Cognitive Assessment (MoCA), and Mini Mental State Exam (MMSE), are implemented. Moreover, a 3DCNN-ML model was trained based on the corresponding cognitive tests and Magnetic Resonance Imaging (MRI) with different modalities using the Alzheimer's Disease Neuroimaging Initiative 2 (ADNI2) dataset and incorporated into the application to predict if the patient suffers from AD. Results: The model has undergone three experiments with different modalities (Cognitive Scores (CS), MRI images, and CS-MRI). As for the CS-MRI experiment, the trained model achieved 97%, 95%, 95%, 96%, and 94% in terms of precision, recall, F1-score, AUC, and accuracy respectively. The considered design notes were also assessed using a new proposed questionnaire based on existing ones in terms of user experience, user interface, mechanics, in-env assistance, and VR induced symptoms and effects. The designed VR system provided an acceptable level of user experience, with participants reporting an enjoyable and immersive experience. While there were areas for improvement, including graphics and sound quality, as well as comfort issues with prolonged HMD use, the user interface and mechanics of the system were generally well-received. Conclusions: The reported results state that our method's comprehensive analysis of 3D brain volumes and incorporation of cognitive scores enabled earlier detection of AD progression, potentially allowing for timely interventions and improved patient outcomes. The proposed integrated system provided us with promising insights for improvements in the diagnosis of AD using technologies. © 2024 | N43: 2024 | O43: 45783.3 | P43: 45783.3 | U43: 255 | W43: Comput. Methods Programs Biomed. | AE43: English | AH43: Scopus | AL43: Publisher: Elsevier Ireland Ltd | AP43: virtual reality; Virtual Reality; Female; Humans; Male; Diagnosis; Patient treatment; Article; human; procedures; Virtual reality; female; male; User interfaces; Users' experiences; aged; artificial intelligence; Artificial Intelligence; deep neural network; comparative study; Disease control; Cognitive assessments; Aged; 3DCNN-ML; accuracy; Aged, 80 and over; Alzheimer disease; Alzheimer Disease; Alzheimer Disease Assessment Scale-cognitive subscale; Alzheimer's disease; Alzheimers disease; Artificial intelligence; classifier; clinical assessment; Cognitive assessment; Cognitive tests; cross validation; dementia assessment; diagnosis; diagnostic imaging; Disease diagnosis; disease exacerbation; disorientation; dizziness; Early diagnosis; Magnetic resonance imaging; Magnetic Resonance Imaging; mechanics; medical history; Mental Status and Dementia Tests; Mini Mental State Examination; Montreal cognitive assessment; Multi-modal data; Multimodal data; nausea; Neurodegenerative diseases; neuroimaging; Neuroimaging; neuropsychological assessment; Neuropsychological Tests; nuclear magnetic resonance imaging; physical examination; Statistical tests; The metaverse; timbre; very elderly
A44: exclude | B44: no access, abstract irrelevant | C44: 89MGCQHA | D44: journalArticle | E44: 2002 | F44: Beconytė, G. | G44: Methodological problems of cartographic representation: Human-centred approach | H44: Land Use Law & Zoning Digest | J44: 00947598 (ISSN) | K44: 10.1080/13921541.2002.10552954 | L44: https://www.scopus.com/inward/record.uri?eid=2-s2.0-85024240857&doi=10.1080%2f13921541.2002.10552954&partnerID=40&md5=099b33032a0ff9b0a145c45ea69ac586 | M44: Applying technologies of automated collection and visualisation (animated, reactive, interactive maps; 3D. virtual reality) it has become possible to represent and update large amounts of diverse, complex geographical data, visualise spatial changes over time and other characteristics which could not appear in static maps. However, the use of new visualisation tools is still limited not only because of the specificity of digital maps but also because of lacking a universal theoretical cognitive framework for both static traditional and digital maps. Main methodological problems related to the quality of cartographic representation also remain unsolved and actually grow bigger as new forms and technologies of visualisation are applied and complexity of represented information grows and range of tasks is extended. Therefore besides the comprehensive usability evaluation throughout the life cycle of a map new models of map design (cartographic representation) that would enable cartographers to take advantage of future technologies and meet users' needs must be elaborated. The purpose of our research is to develop several organisational models, each of them oriented to solution of one of the three above described general problems of cartographic representation in order to improve map quality. This paper provides an overview of the basic challenges for cartographic representation of complex, uncertain, especially qualitative geographic information and main problems recognised during large thematic cartography projects in Vilnius university as well as that discussed during the conference. It is expected to be the start for a more comprehensive study on improving the quality of cartographic representation of complex thematic maps. © 2002 Taylor & Francis Group, LLC. | N44: 2002 | O44: 45783.3 | P44: 45783.3 | R44: 65-69 | T44: 2 | U44: 28 | W44: Land Use Law Zoning Dig. | AE44: English | AH44: Scopus | AP44: Automated collection and visualisation; Cartography; Life cycle of map
A45: for-fulltext | B45: physiological factors | C45: ZZP9U9NR | D45: conferencePaper | E45: 2015 | F45: Bian, Yulong; Yang, Chenglei; Gao, Fengqiang; Li, Hanchao; Sun, Xiaowen; Meng, Xiangxu; Wang, Yu | G45: A Physiological Evaluation Model for Flow-Experience in VR Games: Construction and Preliminary Test | H45: 2015 International Conference on Identification, Information, and Knowledge in the Internet of Things (IIKI) | I45: 978-1-4673-8637-1 | K45: 10.1109/IIKI.2015.59 | L45: http://ieeexplore.ieee.org/document/7428363/ | N45: 2015-10 | O45: 45783.313 | P45: 45783.313 | Q45: 45783.313 | R45: 244-249 | X45: A Physiological Evaluation Model for Flow-Experience in VR Games | AC45: IEEE | AD45: Beijing, China | AJ45: DOI.org (Crossref) | BV45: 2015 International Conference on Identification, Information, and Knowledge in the Internet of Things (IIKI)
A46: exclude | B46: only questionnaires | C46: XM3DACYU | D46: conferencePaper | E46: 2018 | F46: Bellei, Ericles Andrei; Biduski, Daiana; Brock, Lays Andressa; Patricio, Diego Inacio; Souza, Jhonatan De Lima De; Marchi, Ana Carolina Bertoletti De; Rieder, Rafael | G46: Prior Experience as an Influencer in the Momentary User Experience: An Assessment in Immersive Virtual Reality Game Context | H46: 2018 20th Symposium on Virtual and Augmented Reality (SVR) | I46: 978-1-7281-0604-5 | K46: 10.1109/SVR.2018.00014 | L46: https://ieeexplore.ieee.org/document/8802452/ | N46: 2018-10 | O46: 45783.312 | P46: 45783.312 | Q46: 45783.312 | R46: 45901 | X46: Prior Experience as an Influencer in the Momentary User Experience | AC46: IEEE | AD46: Foz do Iguaçu, Brazil | AJ46: DOI.org (Crossref) | BV46: 2018 20th Symposium on Virtual and Augmented Reality (SVR)
A47: exclude | B47: irrelevant | C47: XG398IYF | D47: journalArticle | E47: 2017 | F47: Bellem, H.; Klüver, M.; Schrauf, M.; Schöner, H.-P.; Hecht, H.; Krems, J.F. | G47: Can We Study Autonomous Driving Comfort in Moving-Base Driving Simulators? A Validation Study | H47: Human Factors | J47: 00187208 (ISSN) | K47: 10.1177/0018720816682647 | L47: https://www.scopus.com/inward/record.uri?eid=2-s2.0-85018763192&doi=10.1177%2f0018720816682647&partnerID=40&md5=c6cce87c37814326b70d8806f2ff5a39 | M47: Objective: To lay the basis of studying autonomous driving comfort using driving simulators, we assessed the behavioral validity of two moving-base simulator configurations by contrasting them with a test-track setting. Background: With increasing level of automation, driving comfort becomes increasingly important. Simulators provide a safe environment to study perceived comfort in autonomous driving. To date, however, no studies were conducted in relation to comfort in autonomous driving to determine the extent to which results from simulator studies can be transferred to on-road driving conditions. Method: Participants (N = 72) experienced six differently parameterized lane-change and deceleration maneuvers and subsequently rated the comfort of each scenario. One group of participants experienced the maneuvers on a test-track setting, whereas two other groups experienced them in one of two moving-base simulator configurations. Results: We could demonstrate relative and absolute validity for one of the two simulator configurations. Subsequent analyses revealed that the validity of the simulator highly depends on the parameterization of the motion system. Conclusion: Moving-base simulation can be a useful research tool to study driving comfort in autonomous vehicles. However, our results point at a preference for subunity scaling factors for both lateral and longitudinal motion cues, which might be explained by an underestimation of speed in virtual environments. Application: In line with previous studies, we recommend lateral- and longitudinal-motion scaling factors of approximately 50% to 60% in order to obtain valid results for both active and passive driving tasks. © Human Factors and Ergonomics Society. | N47: 2017 | O47: 45783.3 | P47: 45783.3 | R47: 442-456 | T47: 3 | U47: 59 | W47: Hum. Factors | AE47: English | AH47: Scopus | AL47: Publisher: SAGE Publications Inc. | AP47: Adult; Female; Humans; Male; Middle Aged; automation; Automation; human; Virtual reality; adult; female; male; young adult; Autonomous driving; Immersive environment; reproducibility; Reproducibility of Results; immersive environments; Young Adult; middle aged; Automobile simulators; Driving simulation; trust in automation; Vehicles; driving simulation; Simulators; virtual environments; Vehicle design; car driving; Vehicle automations; Equipment Design; Sensory perception; acceleration; Acceleration; Automobile Driving; autonomous driving; behavioral validity; computer simulation; Computer Simulation; devices; equipment design; methodology; multisensory integration; Multisensory integration; Research Design; usability/acceptance measurement and research; vehicle automation; vehicle design; visual-vestibular integration
A48: exclude | B48: irrelevant | C48: 25YN69UB | D48: journalArticle | E48: 2013 | F48: Bellotti, Francesco; Berta, Riccardo; De Gloria, Alessandro; D'ursi, Annamaria; Fiore, Valentina | G48: A serious game model for cultural heritage | H48: J. Comput. Cult. Herit. | J48: 1556-4673 | K48: 10.1145/2399180.2399185 | L48: https://doi.org/10.1145/2399180.2399185 | M48: Serious games present a promising opportunity for learning, but the genre still lacks methodologies and tools for efficient and low-cost production, particularly for teacher and domain experts. This article gives an authoring framework that aims to provide structured support, from content design to final implementation. In particular, we have abstracted a conceptual model—the SandBox Serious Game - which relies on a generalization of task-based learning theory. The model invites players to perform cognitive tasks contextually while exploring information-rich virtual environments. We consider it particularly suited for cultural heritage entertainment applications. The model defines games that are set in realistic virtual worlds enriched with embedded educational tasks, which we have implemented as minigames. This approach simplifies the authoring work, which can easily be supported by visual authoring tools for ontology-based urban 3D modeling and implementation tasks, thus allowing an approach similar to the mind-maps concept. We propose a top-down methodology for content preparation, starting from a city-level analysis down to the single points of interest and associated tasks, which are instances of simple predefined minigame/quiz typologies. We provide examples and discuss criteria for selecting task typologies according to the authors' cognitive targets. Finally, we discuss the results of a user test, which took place in a lab, aimed at verifying the acquisition of cultural heritage knowledge in a pleasant and engaging way. Games appear particularly suited for supporting the study of images, especially of iconography. Compared to reading text, a game forces the player to focus more strongly on problems, which favors knowledge acquisition and retention. Learning complex concepts requires an investigative attitude, which can be spurred by well-designed games. Good design involves usability, graphic appeal, appropriate content, and the presence of connections which a player must discover in the content. Players should be asked to pay attention to and reason about their whole game activity - including the relationships between the game content, the brief introduction, and concluding texts. More comprehensive tests are needed to better investigate the educational effectiveness—however, the first results are promising, especially in terms of user motivation and creation of new opportunities for learning about CH. | N48: 2013-01 | O48: 45783.306 | P48: 45783.306 | T48: 4 | U48: 5 | AL48: Place: New York, NY, USA Publisher: Association for Computing Machinery | AP48: virtual reality; Serious games; user experience; cultural heritage; user testing; content authoring; game-based learning; task-based learning
A49: exclude | B49: no usability | C49: I3CKGIP9 | D49: conferencePaper | E49: 2019 | F49: Benz, T.M.; Riedl, B.; Chuang, L.L. | G49: Projection displays induce less simulator sickness than head-mounted displays in a real vehicle driving simulator | H49: Proc. - Int. ACM Conf. Automot. User Interfaces Interact. Veh. Appl., AutomotiveUI | I49: 978-145036884-1 (ISBN) | K49: 10.1145/3342197.3344515 | L49: https://www.scopus.com/inward/record.uri?eid=2-s2.0-85073437754&doi=10.1145%2f3342197.3344515&partnerID=40&md5=ad903840afcdbbf4d027b3f7f5432eef | M49: Driving simulators are necessary for evaluating automotive technology for human users. While they can vary in terms of their fidelity, it is essential that users experience minimal simulator sickness and high presence in them. In this paper, we present two experiments that investigate how a virtual driving simulation system could be visually presented within a real vehicle, which moves on a test track but displays a virtual environment. Specifically, we contrasted display presentation of the simulation using either head-mounted displays (HMDs) or fixed displays in the vehicle itself. Overall, we find that fixed displays induced less simulator sickness than HMDs. Neither HMDs or fixed displays induced a stronger presence in our implementation, even when the field-of-view of the fixed display was extended. We discuss the implications of this, particular in the context of scenarios that could induce considerable motion sickness, such as testing non-driving activities in automated vehicles. © 2019 Copyright held by the owner/author(s). Publication rights licensed to ACM. | N49: 2019 | O49: 45783.3 | P49: 45783.3 | R49: 379-387 | AC49: Association for Computing Machinery, Inc | AE49: English | AH49: Scopus | AL49: Journal Abbreviation: Proc. - Int. ACM Conf. Automot. User Interfaces Interact. Veh. Appl., AutomotiveUI | AP49: Diseases; Virtual reality; Helmet mounted displays; Visualization; User interfaces; Driving simulation system; Motion sickness; Automobile simulators; Driving simulation; Vehicles; Street traffic control; Simulator sickness; Head mounted displays; Automotive technology; Flow visualization; HMD; Projection; Projection displays | BV49: Proceedings - 11th International ACM Conference on Automotive User Interfaces and Interactive Vehicular Applications, AutomotiveUI 2019
A50: exclude | B50: only questionnaires | C50: AIJ7DMEI | D50: journalArticle | E50: 2022 | F50: Bernal, I.F.M.; Lozano-Ramírez, N.E.; Cortés, J.M.P.; Valdivia, S.; Muñoz, R.; Aragón, J.; García, R.; Hernández, G. | G50: An Immersive Virtual Reality Training Game for Power Substations Evaluated in Terms of Usability and Engagement | H50: Applied Sciences (Switzerland) | J50: 20763417 (ISSN) | K50: 10.3390/app12020711 | L50: https://www.scopus.com/inward/record.uri?eid=2-s2.0-85122867361&doi=10.3390%2fapp12020711&partnerID=40&md5=217097ec4fcc315985b75292ce5a96ef | M50: Safety-focused training is essential for the operation and maintenance concentrated on the reliability of critical infrastructures, such as power grids. This paper introduces and evaluates a system for power substation operational training by exploring and interacting with realistic models in virtual worlds using serious games. The virtual reality (VR) simulator used building information modelling (BIM) from a 115 kV substation to develop a scenario with high technical detail suitable for professional training. This system created interactive models that could be explored using a first-person-perspective serious game in a cave automatic virtual environment (CAVE). Different operational missions could be carried out in the serious game, allowing several skills to be coached. The suitability for vocational training carried out by utility companies was evaluated in terms of usability and engagement. The evaluation used a System Usability Scale (SUS) and a Game Engagement Questionnaire (GEQ) filled by 16 power substation operators demonstrating marginally acceptable usability, with improvement opportunities and high acceptance (by utility technicians) of this system for operation training focused on safety in such hazardous tasks. © 2022 by the authors. Licensee MDPI, Basel, Switzerland. | N50: 2022 | O50: 45783.3 | P50: 45783.3 | T50: 2 | U50: 12 | W50: Appl. Sci. | AE50: English | AH50: Scopus | AL50: Publisher: MDPI | AP50: Immersive virtual reality; Training; Building information modelling (BIM); Electric power substation; Usability test
A51: exclude | B51: only questionnaires | C51: Q6XTGKHG | D51: conferencePaper | E51: 2021 | F51: Bernardelli, Giuseppina; Flori, Valeria; Greci, Luca; Scaglione, Arianna; Zangiacomi, Andrea | G51: A Virtual Reality Based Application for Children with ADHD: Design and Usability Evaluation | H51: Augmented Reality, Virtual Reality, and Computer Graphics: 8th International Conference, AVR 2021, Virtual Event, September 7–10, 2021, Proceedings | I51: 978-3-030-87594-7 | K51: 10.1007/978-3-030-87595-4_27 | L51: https://doi.org/10.1007/978-3-030-87595-4_27 | M51: This work presents a VR based serious game for children with ADHD and aims at providing an evaluation of the acceptability and the usability of an application developed to create a meaningful and motivating environment for the child, capable of supporting the development of the various attentional components. Due to the Covid-19 pandemic the evaluation was performed online offering also the opportunity to test the feasibility of a validation remotely performed. The expert involved in the study expressed a positive judgment on the application, considering it understandable and easy to use. Moreover, they confirmed that the actions performed by the operator, during the remote sessions, were clear and made it possible to understand the tasks required within by the serious game, thus enabling to provide evidence on such kind of remote validation. | N51: 2021 | O51: 45783.294 | P51: 45784.35 | R51: 363–375 | U51: 12980 | X51: A Virtual Reality Based Application for Children with ADHD | AC51: Springer-Verlag | AD51: Berlin, Heidelberg | AP51: Attention Deficit Hyperactivity Disorder; Cognitive rehabilitation; Serious game; Virtual reality
A52: exclude | B52: only questionnaires | C52: 67274BUM | D52: journalArticle | E52: 2024 | F52: Berthiaume, Maxine; Kinateder, Max; Emond, Bruno; Cooper, Natalia; Obeegadoo, Ishika; Lapointe, Jean-François | G52: Evaluation of a virtual reality training tool for firefighters responding to transportation incidents with dangerous goods | H52: Education and Information Technologies | J52: 1360-2357 | K52: 10.1007/s10639-023-12357-5 | L52: https://doi.org/10.1007/s10639-023-12357-5 | M52: Access to dangerous goods training for firefighters in remote areas is limited for financial and logistical reasons. Virtual reality (VR) is a promising solution for this challenge as it is cost-effective, safe, and allows to simulate realistic scenarios that would be dangerous or difficult to implement in the real world. However, rigorous evaluations of VR training tools for first responders are still scarce. In this exploratory user study, a simple VR training tool involving two dangerous goods scenarios was developed. In each scenario, trainees learned how to safely approach a jackknifed truck with a trailer and how to collect and communicate information about the transported materials. The tool was tested with a group of 24 professional firefighter trainees (n = 22) and instructors (n = 2), who each completed the two training scenarios. The main goal of the study was to assess the usability of the VR tool in the given scenarios. Participants provided feedback on cybersickness, perceived workload, and usability. They also filled out a knowledge test before and after the VR training and gave feedback at the end of the study. The VR tool recorded task completion duration and participants’ navigation and use of tools events. Overall, the tool provided good usability, acceptance, and satisfaction. However, a wide range in individuals’ responses was observed. In addition, no post-training improvement in participants' knowledge was found, likely due to the already high level of knowledge pre-training. Future directions for improving the VR tool, general implications for other VR training tools, and suggestions for future research are discussed. | N52: 2024-01 | O52: 45783.306 | P52: 45783.306 | R52: 14929–14967 | T52: 12 | U52: 29 | AL52: Place: USA Publisher: Kluwer Academic Publishers | AP52: Usability; Virtual reality; Training; Dangerous goods; First responders; Virtual reality evaluation
A53: for-fulltext | B53: head rotation frequency | C53: 45EZDBPC | D53: conferencePaper | E53: 2020 | F53: Hynes, E.; Flynn, R.; Lee, B.; Murray, N. | G53: A QoE Evaluation of an Augmented Reality Procedure Assistance Application | H53: Int. Conf. Qual. Multimed. Exp., QoMEX | I53: 978-172815965-2 (ISBN) | K53: 10.1109/QoMEX48832.2020.9123097 | L53: https://www.scopus.com/inward/record.uri?eid=2-s2.0-85087666173&doi=10.1109%2fQoMEX48832.2020.9123097&partnerID=40&md5=b409a3bfc9b2f8eb5e36b4adb72a5dd6 | M53: Augmented reality (AR) is a key technology to enhance worker effectiveness during increasing automation of repetitive jobs in the workplace. AR will achieve this by assisting the user to successfully perform complex and frequently changing procedures. The design of AR applications for these roles is critical to their acceptability and utility. User quality of experience (QoE) will inform these design decisions. A user arrives at a quality judgment upon post-experience reflection of their degree of delight or annoyance relating to the degree of fulfilment of pragmatic and hedonic needs and expectations of the medium under consideration. QoE researchers have largely depended upon post-experience subjective reports to determine the user's QoE. Subjective reports have been shown to be biased by primacy, recency and maxima of experience stimuli. Recent research involves the identification of implicit metrics that can be used to determine user QoE continuously during a multimedia experience. This work evaluates head rotation frequency as an objective metric of user QoE. The literature shows that emotion is expressed in the frequency of a person's head rotation around three axes of movement (pitch, yaw and roll). Low frequency head rotation has been shown to include expression of happy emotion while high frequency exclusively expresses anger emotion. These emotions are analogous to those reflected on by a user during the quality formation process. This demo paper analyses the amount of high frequency head rotation exhibited by the user upon task completion using an AR procedure assistance application or a paper-based control. An optimal Rubik's Cube solving AR application was used as a proof of concept for AR-based procedure assistance. Preliminary results showed that the AR environment yielded higher task success rates and significantly shorter task completion durations. The AR users exhibited significantly lower amplitudes of anger frequencies in their head rotations than the control group. © 2020 IEEE. | N53: 2020 | O53: 45783.3 | P53: 45783.3 | AC53: Institute of Electrical and Electronics Engineers Inc. | AE53: English | AH53: Scopus | AL53: Journal Abbreviation: Int. Conf. Qual. Multimed. Exp., QoMEX | AP53: augmented reality; Augmented reality; User experience; Proof of concept; affective state; Key technologies; Multimedia systems; quality of experience; Quality of experience (QoE); Quality of service; Control groups; Design decisions; Formation process; head-rotation frequency; High frequency HF; Recent researches; Rotation | BV53: 2020 12th International Conference on Quality of Multimedia Experience, QoMEX 2020
A54: for-fulltext | B54: usability evaluation unclear, read fulltext | C54: Y4FYC9JB | D54: conferencePaper | E54: 2001 | F54: Suomela, Riku; Lehikoinen, Juha; Salminen, Ilkka | G54: A System for Evaluating Augmented Reality User Interfaces in Wearable Computers | H54: Proceedings of the 5th IEEE International Symposium on Wearable Computers | I54: 0-7695-1318-2 | M54: Usability tests with wearable computers are difficult to conduct due to the nature of wearable computers. Wearable computers are intended for personal use and the test supervisor does not know exactly what the test subject is currently seeing in augmented reality through the head-worn display of the wearable computer. Due to this personal nature, the concepts of traditional usability testing need some rethinking. This paper presents a combination of techniques that connects the computers of the test subject and the supervisor. Both of the computers share the same view of augmented reality and the supervisor knows exactly what the user is doing and what state the computer is in. All actions and sensor data are also recorded for later analysis. Complete usability tests have been made with this system and the system fulfilled its goals | N54: 2001 | O54: 45783.306 | P54: 45783.306 | R54: 77 | Y54: ISWC '01 | AC54: IEEE Computer Society | AD54: USA | AP54: augmented reality; usability testing; telepresence; wearable computer
A55: for-fulltext | B55: automation unclear, read fulltext | C55: IQN8MSH8 | D55: journalArticle | E55: 2024 | F55: Woo, J.; Shidara, K.; Achard, C.; Tanaka, H.; Nakamura, S.; Pelachaud, C. | G55: Adaptive virtual agent: Design and evaluation for real-time human-agent interaction | H55: International Journal of Human Computer Studies | J55: 10715819 (ISSN) | K55: 10.1016/j.ijhcs.2024.103321 | L55: https://www.scopus.com/inward/record.uri?eid=2-s2.0-85197034932&doi=10.1016%2fj.ijhcs.2024.103321&partnerID=40&md5=10e63a327555aae02d722d96d074f25d | M55: When we converse, we adapt our behaviors to our interlocutors. The adaptation can serve to indicate our engagement which can also elicit enhancement of the involvement of others. Virtual agents (or socially interactive virtual agents) that play the role of interaction partners can improve the human users’ interaction experience by displaying continuous and adaptive behaviors in real time. Virtual agents have been used in multiple domains to improve user interaction and performance. The promising results of the endowment of adaptation to agents in increasing the agents’ perception and user experience were shown in previous studies. In this paper, we develop an adaptive virtual agent that renders real-time adaptive behaviors based on the behaviors shown by its human interlocutor. The ASAP model rendering reciprocally adaptive agent behavior was employed to realize the system. The system consists of four main parts: perception of social signals, agent adaptive behavior generation, agent visualization (i.e. rendering of the agent's verbal and nonverbal behavior), and communication of signals. To showcase the usefulness of our adaptive agent, as a proof-of-concept we choose the e-health application of cognitive behavior therapy (CBT), which identifies and rectifies biased and irrational thoughts (or automatic thoughts). Through this study, we show the importance of giving the agent reciprocal adaptation capability notably in enhancing the user experience and the effectiveness of the CBT session. We validate the importance of endowing such adaptation capability by studying the difference between agents that are reciprocally adaptive, solely expressive (with mismatched behavior), and inexpressive (in a still posture) via questionnaires and measures related to the agent perception (naturalness, human-likeliness, synchrony, and engagement) for user experience and the CBT effectiveness (mood, anxiety, stress, and cognitive change). These results highlight the value of making virtual agents adapt in real time. This could lead to agents being capable of providing more personalized and interactive experiences for a wide range of applications. Also, we have collected a new human-agent interaction (HAI) database, HAI-CBT database, which is publicly available to the research community. © 2024 The Authors | N55: 2024 | O55: 45783.3 | P55: 45783.3 | U55: 190 | W55: Int J Hum Comput Stud | AE55: English | AH55: Scopus | AL55: Publisher: Academic Press | AP55: Virtual reality; Users' experiences; Adaptation; Adaptive behaviour; Behavioral research; Cognitive behavior therapy; Cognitive-behavior therapies; Facial expressions; Facial Expressions; Human-agent interaction; Interactive agents; Real- time; Rendering (computer graphics); Socially interactive agent; Socially interactive agent (SIA); Virtual agent
A56: exclude | B56: only questionnaires | C56: MSUVI9LS | D56: journalArticle | E56: 2024 | F56: Birrenbach, T.; Stuber, R.; Müller, C.E.; Sutter, P.-M.; Hautz, W.E.; Exadaktylos, A.K.; Müller, M.; Wespi, R.; Sauter, T.C. | G56: Virtual reality simulation to enhance advanced trauma life support trainings – a randomized controlled trial | H56: BMC Medical Education | J56: 14726920 (ISSN) | K56: 10.1186/s12909-024-05645-2 | L56: https://www.scopus.com/inward/record.uri?eid=2-s2.0-85196104706&doi=10.1186%2fs12909-024-05645-2&partnerID=40&md5=43528d928ab2a5d57cff7d44a26ab58c | M56: Background: Advanced Trauma Life Support (ATLS) is the gold standard of initial assessment of trauma patients and therefore a widely used training program for medical professionals. Practical application of the knowledge taught can be challenging for medical students and inexperienced clinicians. Simulation-based training, including virtual reality (VR), has proven to be a valuable adjunct to real-world experiences in trauma education. Previous studies have demonstrated the effectiveness of VR simulations for surgical and technical skills training. However, there is limited evidence on VR simulation training specifically for trauma education, particularly within the ATLS curriculum. The purpose of this pilot study is to evaluate the feasibility, effectiveness, and acceptance of using a fully immersive VR trauma simulation to prepare medical students for the ATLS course. Methods: This was a prospective randomised controlled pilot study on a convenience sample of advanced medical students (n = 56; intervention group with adjunct training using a commercially available semi-automated trauma VR simulation, n = 28, vs control group, n = 28) taking part in the ATLS course of the Military Physician Officer School. Feasibility was assessed by evaluating factors related to technical factors of the VR training (e.g. rate of interruptions and premature termination). Objective and subjective effectiveness was assessed using confidence ratings at four pre-specified points in the curriculum, validated surveys, clinical scenario scores, multiple choice knowledge tests, and ATLS final clinical scenario and course pass rates. Acceptance was measured using validated instruments to assess variables of media use (Technology acceptance, usability, presence and immersion, workload, and user satisfaction). Results: The feasibility assessment demonstrated that only one premature termination occurred and that all remaining participants in the intervention group correctly stabilised the patient. No significant differences between the two groups in terms of objective effectiveness were observed (p = 0.832 and p = 0.237 for the pretest and final knowledge test, respectively; p = 0.485 for the pass rates for the final clinical scenario on the first attempt; all participants passed the ATLS course). In terms of subjective effectiveness, the authors found significantly improved confidence post-VR intervention (p <.001) in providing emergency care using the ATLS principles. Perceived usefulness in the TEI was stated with a mean of 4 (SD 0.8; range 0–5). Overall acceptance and usability of the VR simulation was rated as positive (System Usability Scale total score mean 79.4 (SD 11.3, range 0–100). Conclusions: The findings of this prospective pilot study indicate the potential of using VR trauma simulations as a feasible and acceptable supplementary tool for the ATLS training course. Where objective effectiveness regarding test and scenario scores remained unchanged, subjective effectiveness demonstrated improvement. Future research should focus on identifying specific scenarios and domains where VR can outperform or enhance traditional learning methods in trauma simulation. © The Author(s) 2024. | N56: 2024 | O56: 45783.3 | P56: 45783.3 | T56: 1 | U56: 24 | W56: BMC Med. Educ. | AE56: English | AH56: Scopus | AL56: Publisher: BioMed Central Ltd | AP56: virtual reality; Virtual Reality; Adult; Female; Humans; Male; controlled study; human; Virtual reality; adult; female; male; young adult; Pilot Projects; pilot study; Prospective Studies; prospective study; medical student; Young Adult; education; Feasibility Studies; feasibility study; Simulation; advanced trauma life support; Advanced Trauma Life Support Care; ATLS; clinical competence; Clinical Competence; curriculum; Curriculum; Educational Measurement; Medical education; randomized controlled trial; simulation training; Simulation Training; Students, Medical; Trauma management
A57: exclude | B57: only questionnaires | C57: 273N6HUB | D57: journalArticle | E57: 2023 | F57: Birrenbach, T.; Wespi, R.; Hautz, W. E.; Berger, J.; Schwab, P. R.; Papagiannakis, G.; Exadaktylos, A. K.; Sauter, T. C. | G57: Development and usability testing of a fully immersive VR simulation for REBOA training | H57: International Journal of Emergency Medicine | J57: 1865-1380 | K57: 10.1186/s12245-023-00545-6 | L57: https://intjem.biomedcentral.com/articles/10.1186/s12245-023-00545-6 | M57: Abstract Background Resuscitative endovascular balloon occlusion of the aorta (REBOA) is a potentially life-saving procedure for bleeding trauma patients. Being a rare and complex procedure performed in extreme situations, repetitive training of REBOA teams is critical. Evidence-based guidelines on how to train REBOA are missing, although simulation-based training has been shown to be effective but can be costly and complex. We aimed to determine the feasibility and acceptance of REBOA training using a fully immersive virtual reality (VR) REBOA simulation, as well as assess the confidence in conducting the REBOA procedure before and after the training. Methods Prospective feasibility pilot study of prehospital emergency physicians and paramedics in Bern, Switzerland, from November 2020 until March 2021. Baseline characteristics of trainees, prior training and experience in REBOA and with VR, variables of media use (usability: system usability scale, immersion/presence: Slater-Usoh-Steed, workload: NASA-TLX, user satisfaction: USEQ) as well as confidence prior and after VR training were accessed. Results REBOA training in VR was found to be feasible without relevant VR-specific side-effects. Usability (SUS median 77.5, IQR 71.3–85) and sense of presence and immersion (Slater-Usoh-Steed median 4.8, IQR 3.8–5.5) were good, the workload without under-nor overstraining (NASA-TLX median 39, IQR 32.8–50.2) and user satisfaction high (USEQ median 26, IQR 23–29). Confidence of trainees in conducting REBOA increased significantly after training ( p < 0.001). Conclusions Procedural training of the REBOA procedure in immersive virtual reality is possible with a good acceptance and high usability. REBOA VR training can be an important part of a training curriculum, with the virtual reality-specific advantages of a time- and instructor-independent learning. | N57: 45205 | O57: 45783.293 | P57: 45783.293 | Q57: 45783.293 | R57: 67 | T57: 1 | U57: 16 | W57: Int J Emerg Med | AE57: en | AJ57: DOI.org (Crossref) | AN57: /Users/dennis/Zotero/storage/CLJFYS47/Birrenbach et al. - 2023 - Development and usability testing of a fully immersive VR simulation for REBOA training.pdf
A58: exclude | B58: only questionnaires | C58: 2I5UAFMW | D58: conferencePaper | E58: 2020 | F58: Boletsis, Costas | G58: A User Experience Questionnaire for VR Locomotion: Formulation and Preliminary Evaluation | H58: Augmented Reality, Virtual Reality, and Computer Graphics: 7th International Conference, AVR 2020, Lecce, Italy, September 7–10, 2020, Proceedings, Part I | I58: 978-3-030-58464-1 | K58: 10.1007/978-3-030-58465-8_11 | L58: https://doi.org/10.1007/978-3-030-58465-8_11 | M58: When evaluating virtual reality (VR) locomotion techniques, the user experience metrics that are used are usually either focused on specific experiential dimensions or based on non-standardised, subjective reporting. The field would benefit from a standard questionnaire for evaluating the general user experience of VR locomotion techniques. This paper presents a synthesised user experience questionnaire for VR locomotion, which is called the VR Locomotion Experience Questionnaire (VRLEQ). It comprises the Game Experience Questionnaire (GEQ) and the System Usability Scale (SUS) survey. The results of the VRLEQ’s application in a comparative, empirical study () of three prevalent VR locomotion techniques are described. The questionnaire’s content validity is assessed at a preliminary level based on the correspondence between the questionnaire items and the qualitative results from the study’s semi-structured interviews. VRLEQ’s experiential dimensions’ scoring corresponded well with the semi-structured interview remarks and effectively captured the experiential qualities of each VR locomotion technique. The VRLEQ results facilitated and quantified comparisons between the techniques and enabled an understanding of how the techniques performed in relation to each other. | N58: 2020 | O58: 45783.294 | P58: 45784.33 | R58: 157–167 | AC58: Springer-Verlag | AD58: Berlin, Heidelberg | AL58: event-place: Lecce, Italy | AN58: /Users/dennis/Zotero/storage/GTKAL8QS/Boletsis - 2020 - A User Experience Questionnaire for VR Locomotion Formulation and Preliminary Evaluation.pdf | AP58: Locomotion; Questionnaire; User experience; Virtual reality
A59: exclude | B59: only questionnaires | C59: CRKMLL37 | D59: conferencePaper | E59: 2018 | F59: Borman, Rohmat Indra; Putra, Yogi Purnomo; Fernando, Yusra; Kurniawan, Dwi Ely; Prasetyawan, Purwono; Ahmad, Imam | G59: Designing an Android-based Space Travel Application Trough Virtual Reality for Teaching Media | H59: 2018 International Conference on Applied Engineering (ICAE) | I59: 978-1-5386-8066-7 | K59: 10.1109/INCAE.2018.8579394 | L59: https://ieeexplore.ieee.org/document/8579394/ | N59: 2018-10 | O59: 45783.312 | P59: 45783.312 | Q59: 45783.312 | R59: 45778 | AC59: IEEE | AD59: Batam | AJ59: DOI.org (Crossref) | BV59: 2018 International Conference on Applied Engineering (ICAE)
A60: exclude | B60: only questionnaires | C60: 82N7NVVV | D60: conferencePaper | E60: 2018 | F60: Botella, Federico; Peñalver, Antonio; Borrás, Fernando | G60: Evaluating the usability and acceptance of an AR app in learning Chemistry for Secondary Education | H60: Proceedings of the XIX International Conference on Human Computer Interaction | I60: 978-1-4503-6491-1 | K60: 10.1145/3233824.3233838 | L60: https://doi.org/10.1145/3233824.3233838 | M60: Teaching concepts that require the manipulation or visualization of objects that are not available to everyone because of their abstract, scientific or spatial nature present some limitations. Augmented reality and mobile devices are tools available today that allow solving these shortcomings and offer the possibility of interacting with virtual objects in a three-dimensional space. In this paper, we present an author tool for teaching Chemistry in Secondary Education, using augmented reality and then we provide the results of the evaluation of usability that we conducted with 12 high school students in order to evaluate the usability and user experience of the developed app. We have found in this study that, surprisingly, it seems that users of iOS mobiles are better to manipulate AR objects in 3D using the Android mobile we used in this experiment. | N60: 2018 | O60: 45783.306 | P60: 45783.306 | Y60: Interacción '18 | AC60: Association for Computing Machinery | AD60: New York, NY, USA | AL60: event-place: Palma, Spain | AP60: Augmented Reality; Usability evaluation; mobile app; HCI; mobile devices; SUS
A61: for-fulltext | B61: agent based | C61: 8XQPPFLB | D61: conferencePaper | E61: 2020 | F61: Prada, Rui; Prasetya, I. S. W. B.; Kifetew, Fitsum; Dignum, Frank; Vos, Tanja E. J.; Lander, Jason; Donnart, Jean-yves; Kazmierowski, Alexandre; Davidson, Joseph; Fernandes, Pedro M. | G61: Agent-based Testing of Extended Reality Systems | H61: 2020 IEEE 13th International Conference on Software Testing, Validation and Verification (ICST) | I61: 978-1-7281-5778-8 | K61: 10.1109/ICST46399.2020.00051 | L61: https://ieeexplore.ieee.org/document/9159086/ | N61: 2020-10 | O61: 45783.311 | P61: 45783.382 | Q61: 45783.311 | R61: 414-417 | AC61: IEEE | AD61: Porto, Portugal | AF61: https://ieeexplore.ieee.org/Xplorehelp/downloads/license-information/IEEE.html | AJ61: DOI.org (Crossref) | AN61: /Users/dennis/Zotero/storage/JTS253ZV/Prada et al. - 2020 - Agent-based Testing of Extended Reality Systems.pdf | AP61: User experience; Software testing; Reality systems; Cognitive tests; Iterative design; Verification; Autonomous agents; User experiences (ux); Quality assurance; agent-based testing; Agent-based testing; AI-based testing; testing computer game; Testing procedure; testing virtual reality; user experience testing | BV61: 2020 IEEE 13th International Conference on Software Testing, Validation and Verification (ICST)
A62: for-fulltext | B62: usability evaluation unclear, read fulltext | C62: 5EQEXLYT | D62: journalArticle | E62: 2024 | F62: Zou, L.; Liang, T. | G62: Algorithm Optimization of Computer Simulation Vehicle Driving Simulation System Based on Virtual Reality Technology | H62: International Journal of Computational Intelligence Systems | J62: 18756891 (ISSN) | K62: 10.1007/s44196-024-00426-7 | L62: https://www.scopus.com/inward/record.uri?eid=2-s2.0-85185398111&doi=10.1007%2fs44196-024-00426-7&partnerID=40&md5=6d9eea32a36972e57c0e047455f2bd1b | M62: The traditional automobile driving simulation system has the problems of low calculation efficiency and lack of realism. The traditional automobile driving simulation system with low computational efficiency and lack of realism limits the learning effect. Through virtual reality technology, vehicle driving can be simulated. By optimizing the algorithm of simulating vehicle driving simulation system, the preference of testers for driving style is investigated and the driver's preference style is determined. Finally, through the automatic driving simulation test method based on genetic algorithm, the key scenes can be divided into 11 different types, and the Euclidean distance of these 11 types is analyzed. Most drivers prefer a more conservative autonomous driving style. When analyzing 11 key scenario types, the Euclidean distance between scenario 2 and scenario 3 is the smallest, which is 33 m, and the maximum Euclidean distance between scenario 6 and scenario 11 is 91 m. The difference between scene 2 and scene 3 is the smallest, while the difference between scene 6 and scene 11 is the largest, and there are differences between each scene. Through virtual reality technology and algorithm optimization, the performance and user experience of driving simulation system are improved. © The Author(s) 2024. | N62: 2024 | O62: 45783.3 | P62: 45783.3 | T62: 1 | U62: 17 | W62: Int. J. Comput. Intell. Syst. | AE62: English | AH62: Scopus | AL62: Publisher: Springer Science and Business Media B.V. | AP62: Virtual reality technology; Virtual reality; Autonomous driving; User interfaces; Algorithms optimizations; Automobile drivers; Automobile driving; Autonomous vehicles; Calculation efficiency; Computational efficiency; Computer simulation; Driving simulation system; Driving styles; Euclidean distance; Genetic algorithms; Questionnaire survey; Questionnaire surveys; Vehicle driving simulation system; Virtual Reality Technology
A63: exclude | B63: no evaluation | C63: WK2LVT6A | D63: conferencePaper | E63: 2013 | F63: Boy, Guy Andre; Platt, Donald | G63: A situation awareness assistant for human deep space exploration | H63: Proceedings of the 15th International Conference on Human-Computer Interaction: Interaction Modalities and Techniques - Volume Part IV | I63: 978-3-642-39329-7 | K63: 10.1007/978-3-642-39330-3_68 | L63: https://doi.org/10.1007/978-3-642-39330-3_68 | M63: This paper presents the development and testing of a Virtual Camera (VC) system to improve astronaut and mission operations situation awareness while exploring other planetary bodies. In this embodiment, the VC is implemented using a tablet-based computer system to navigate through interactive database application. It is claimed that the advanced interaction media capability of the VC can improve situation awareness as the distribution of human space exploration roles change in deep space exploration. The VC is being developed and tested for usability and capability to improve situation awareness. Work completed thus far as well as what is needed to complete the project will be described. Planned testing will also be described. | N63: 2013 | O63: 45783.306 | P63: 45783.306 | R63: 629–636 | Y63: HCI'13 | AC63: Springer-Verlag | AD63: Berlin, Heidelberg | AL63: event-place: Las Vegas, NV | AP63: augmented reality; usability testing; human-computer interaction (HCI); situation awareness (SA); space exploration; tablet computing
A64: exclude | B64: only questionnaires | C64: 55USFHUN | D64: conferencePaper | E64: 2021 | F64: Bozgeyikli, Evren; Bozgeyikli, Lal Lila | G64: Evaluating Object Manipulation Interaction Techniques in Mixed Reality: Tangible User Interfaces and Gesture | H64: 2021 IEEE Virtual Reality and 3D User Interfaces (VR) | I64: 978-1-6654-1838-6 | K64: 10.1109/VR50410.2021.00105 | L64: https://ieeexplore.ieee.org/document/9417663/ | N64: 2021-03 | O64: 45783.312 | P64: 45783.312 | Q64: 45783.312 | R64: 778-787 | X64: Evaluating Object Manipulation Interaction Techniques in Mixed Reality | AC64: IEEE | AD64: Lisboa, Portugal | AF64: https://ieeexplore.ieee.org/Xplorehelp/downloads/license-information/IEEE.html | AJ64: DOI.org (Crossref) | BV64: 2021 IEEE Virtual Reality and 3D User Interfaces (VR)
A65: exclude | B65: only questionnaires | C65: CAM7SGZ2 | D65: conferencePaper | E65: 2022 | F65: Bozgeyikli, Lal Lila; Bozgeyikli, Evren | G65: Tangiball: Foot-Enabled Embodied Tangible Interaction with a Ball in Virtual Reality | H65: 2022 IEEE Conference on Virtual Reality and 3D User Interfaces (VR) | I65: 978-1-6654-9617-9 | K65: 10.1109/VR51125.2022.00103 | L65: https://ieeexplore.ieee.org/document/9756808/ | N65: 2022-03 | O65: 45783.313 | P65: 45783.313 | Q65: 45783.313 | R65: 812-820 | X65: Tangiball | AC65: IEEE | AD65: Christchurch, New Zealand | AF65: https://doi.org/10.15223/policy-029 | AJ65: DOI.org (Crossref) | BV65: 2022 IEEE on Conference Virtual Reality and 3D User Interfaces (VR)
A66: for-fulltext | B66: physiological factors | C66: E5DH679C | D66: conferencePaper | E66: 2018 | F66: He, Linjia; Li, Hongsong; Xue, Tong; Sun, Deyuan; Zhu, Shoulun; Ding, Gangyi | G66: Am I in the theater? usability study of live performance based virtual reality | H66: Proceedings of the 24th ACM Symposium on Virtual Reality Software and Technology | I66: 978-1-4503-6086-9 | K66: 10.1145/3281505.3281508 | L66: https://doi.org/10.1145/3281505.3281508 | M66: Duplicating the audience experience of an art performance with VR technology is a promising VR application, which is considered to provide better viewer experience than the conventional video. As various forms of art performances are recorded by the panoramic camera and broadcasted on the Internet, the impact of this new VR-based media to the viewers needs to be systematically studied. In this work, a two-level usability framework is proposed, which combines the traditional concepts of presence and the quality evaluation of art performances, aiming to systematically study the usability of such VR application. Both the conventional video and the panoramic video of a theatre performance were captured simultaneously, and were replayed to two groups of viewers in a cinematic setup and through an HMD respectively. The psychological measurement methods, including the questionnaire and the interview, as well as the psychophysical measurement methods, including the EEG and the motion capture techniques were both used in the study. The results show that the such VR application duplicates the live performance better by providing a higher sense of presence, higher engagement levels, and stronger desire to see live performance. For visual intensive performance contents, the new VR-based media can provide a better user experience. The future development of the new media forms based on the panoramic video technique could benefit from this work. | N66: 2018 | O66: 45783.306 | P66: 45783.306 | Y66: VRST '18 | AC66: Association for Computing Machinery | AD66: New York, NY, USA | AL66: event-place: Tokyo, Japan | AP66: virtual reality; EEG; usability evaluation; live performance; viewer experience
A67: exclude | B67: only questionnaires | C67: DFB6VL79 | D67: conferencePaper | E67: 2025 | F67: Brade, Jennifer; Kögel, Alexander; Klimant, Franziska; Dix, Martin | G67: Pedaling into Presence: Evaluating Presence and User Experience in VR Cycling vs. Controller Use | H67: 2025 IEEE Conference on Virtual Reality and 3D User Interfaces Abstracts and Workshops (VRW) | I67: 979-8-3315-1484-6 | K67: 10.1109/VRW66409.2025.00308 | L67: https://ieeexplore.ieee.org/document/10972758/ | N67: 45724 | O67: 45783.311 | P67: 45783.311 | Q67: 45783.311 | R67: 324-325 | X67: Pedaling into Presence | AC67: IEEE | AD67: Saint Malo, France | AF67: https://doi.org/10.15223/policy-029 | AJ67: DOI.org (Crossref) | BV67: 2025 IEEE Conference on Virtual Reality and 3D User Interfaces Abstracts and Workshops (VRW)
A68: exclude | B68: only questionnaires | C68: FD8V9JD6 | D68: conferencePaper | E68: 2015 | F68: Brancati, Nadia; Caggianese, Giuseppe; Pietro, Giuseppe De; Frucci, Maria; Gallo, Luigi; Neroni, Pietro | G68: Usability Evaluation of a Wearable Augmented Reality System for the Enjoyment of the Cultural Heritage | H68: 2015 11th International Conference on Signal-Image Technology & Internet-Based Systems (SITIS) | I68: 978-1-4673-9721-6 | K68: 10.1109/SITIS.2015.98 | L68: http://ieeexplore.ieee.org/document/7400650/ | N68: 2015-11 | O68: 45783.306 | P68: 45784.286 | Q68: 45783.311 | R68: 768-774 | AC68: IEEE | AD68: Bangkok, Thailand | AJ68: DOI.org (Crossref) | BV68: 2015 11th International Conference on Signal-Image Technology & Internet-Based Systems (SITIS)
A69: exclude | B69: only questionnaires | C69: IIAQTJJD | D69: conferencePaper | E69: 2020 | F69: Brice, Daniel; Rafferty, Karen; McLoone, Seán | G69: AugmenTech: The Usability Evaluation of an AR System for Maintenance in Industry | H69: Augmented Reality, Virtual Reality, and Computer Graphics: 7th International Conference, AVR 2020, Lecce, Italy, September 7–10, 2020, Proceedings, Part II | I69: 978-3-030-58467-2 978-3-030-58468-9 | K69: 10.1007/978-3-030-58468-9_21 | L69: https://link.springer.com/10.1007/978-3-030-58468-9_21 | N69: 2020 | O69: 45783.294 | P69: 45784.35 | Q69: 45783.294 | R69: 284-303 | U69: 12243 | X69: AugmenTech | AC69: Springer International Publishing | AD69: Cham | AE69: en | AJ69: DOI.org (Crossref) | AL69: Series Title: Lecture Notes in Computer Science | AP69: AR training; Maintenance; Usability testing | AR69: De Paolis, Lucio Tommaso; Bourdot, Patrick
A70: exclude | B70: irrelevant | C70: TJATBQ82 | D70: conferencePaper | E70: 2020 | F70: Brzeski, A.; Cychnerski, J.; Draszawka, K.; Dziubich, K.; Dziubich, T.; Korłub, W.; Rościszewski, P. | G70: Automated Classifier Development Process for Recognizing Book Pages from Video Frames | H70: Commun. Comput. Info. Sci. | I70: 18650929 (ISSN); 978-303055813-0 (ISBN) | K70: 10.1007/978-3-030-55814-7_14 | L70: https://www.scopus.com/inward/record.uri?eid=2-s2.0-85090094980&doi=10.1007%2f978-3-030-55814-7_14&partnerID=40&md5=c259c7f93fa119e858671aac42aed6be | M70: One of the latest developments made by publishing companies is introducing mixed and augmented reality to their printed media (e.g. to produce augmented books). An important computer vision problem that they are facing is classification of book pages from video frames. The problem is non-trivial, especially considering that typical training data is limited to only one digital original per book page, while the trained classifier should be suitable for real-time utilization on mobile devices, where camera can be exposed to highly diverse conditions and computing resources are limited. In this paper we address this problem by proposing an automated classifier development process that allows training classification models that run real-time, with high usability, on low-end mobile devices and achieve average accuracy of 88.95% on our in-house developed test set consisting of over 20 000 frames from real videos of 5 books for children. At the same time, deployment tests reveal that the classifier development process time is reduced approximately 16-fold. © 2020, Springer Nature Switzerland AG. | N70: 2020 | O70: 45783.3 | P70: 45783.3 | R70: 169-179 | U70: 1260 CCIS | AC70: Springer | AE70: English | AH70: Scopus | AL70: Journal Abbreviation: Commun. Comput. Info. Sci. | AP70: Augmented reality; Classification models; Convolutional neural networks; Digital libraries; Development process; Machine learning; Classification (of information); Augmented book; Automated classifiers; Book page classification; Business information management; Computation theory; Computer vision; Computer vision problems; Computing resource; Digital devices; Latest development; Mixed and augmented realities | AR70: Bellatreche L.; Bieliková M.; Boussaïd O.; Darmont J.; Catania B.; Demidova E.; Duchateau F.; Hall M.; Mercun T.; Žumer M.; Novikov B.; Papatheodorou C.; Risse T.; Romero O.; Sautot L.; Talens G.; Wrembel R. | BV70: Communications in Computer and Information Science
A71: exclude | B71: irrelevant | C71: RTWS79KD | D71: journalArticle | E71: 2014 | F71: Bugarić, Marin; Jakovčević, Toni; Stipaničev, Darko | G71: Adaptive estimation of visual smoke detection parameters based on spatial data and fire risk index | H71: Computer Vision and Image Understanding | J71: 1077-3142 | K71: 10.1016/j.cviu.2013.10.003 | L71: https://doi.org/10.1016/j.cviu.2013.10.003 | M71: Standard wildfire smoke detection systems detect fires using remote cameras located at observation posts. Images from the cameras are analyzed using standard computer vision techniques, and human intervention is required only in situations in which the system raises an alarm. The number of alarms depends largely on manually set detection sensitivity parameters. One of the primary drawbacks of this approach is the false alarm rate, which impairs the usability of the system. In this paper, we present a novel approach using GIS and augmented reality to include the spatial and fire risk data of the observed scene. This information is used to improve the reliability of the existing systems through automatic parameter adjustment. For evaluation, three smoke detection methods were improved using this approach and compared to the standard versions. The results demonstrated significant improvement in different smoke detection aspects, including detection range, rate of correct detections and decrease in the false alarm rate. | N71: 2014-01 | O71: 45783.306 | P71: 45783.382 | R71: 184–196 | U71: 118 | AL71: Place: USA Publisher: Elsevier Science Inc. | AP71: Augmented reality; Geographic information systems; Errors; Image analysis; Cameras; GIS; Adaptive estimation; Computer vision techniques; Detection sensitivity; Fires; Human intervention; Parameter adjustments; Risk perception; Smoke detection; Smoke detectors; Standard versions; Wildfire
A72: exclude | B72: irrelevant | C72: YVHJI2F2 | D72: conferencePaper | E72: 2016 | F72: Bushnevskiy, A.; Sorgi, L.; Rosenhahn, B. | G72: Multicamera Calibration from Visible and Mirrored Epipoles | H72: Proc IEEE Comput Soc Conf Comput Vision Pattern Recognit | I72: 10636919 (ISSN); 978-146738850-4 (ISBN) | K72: 10.1109/CVPR.2016.367 | L72: https://www.scopus.com/inward/record.uri?eid=2-s2.0-84986268777&doi=10.1109%2fCVPR.2016.367&partnerID=40&md5=e14fc461b0befbc9a40b1ad0db1a5850 | M72: Multicamera rigs are used in a large number of 3D Vision applications, such as 3D modeling, motion capture or telepresence and a robust calibration is of utmost importance in order to achieve a high accuracy results. In many practical configurations the cameras in a rig are arranged in such a way, that they can observe each other, in other words a number of epipoles correspond to the real image points. In this paper we propose a solution for the automatic recovery of the external calibration of a multicamera system by enforcing only simple geometrical constraints, arising from the epipole visibility, without using any calibration object, such as checkerboards, laser pointers or similar. Additionally, we introduce an extension of the method that handles the case of epipoles being visible in the reflection of a planar mirror, which makes the algorithm suitable for the calibration of any multicamera system, irrespective of the number of cameras and their actual mutual visibility, and furthermore we remark that it requires only one or a few images per camera and therefore features a high speed and usability. We produce an evidence of the algorithm effectiveness by presenting a wide set of tests performed on synthetic as well as real datasets and we compare the results with those obtained using a traditional LED-based algorithm. The real datasets have been captured using a multicamera Virtual Reality (VR) rig and a spherical dome configuration for 3D reconstruction. © 2016 IEEE. | N72: 2016 | O72: 45783.3 | P72: 45783.3 | R72: 3373-3381 | U72: 2016-December | AC72: IEEE Computer Society | AE72: English | AH72: Scopus | AL72: Journal Abbreviation: Proc IEEE Comput Soc Conf Comput Vision Pattern Recognit | AP72: Virtual reality; Three dimensional computer graphics; Visual communication; Cameras; Computer vision; Visibility; Calibration; 3D reconstruction; Automatic recovery; External calibration; Geometrical constraints; Multi-camera calibration; Multi-camera rigs; Multicamera systems; Pattern recognition; Robust calibration | BV72: Proceedings of the IEEE Computer Society Conference on Computer Vision and Pattern Recognition
A73: exclude | B73: no evaluation | C73: LP5Y6CJ2 | D73: conferencePaper | E73: 2006 | F73: Cai, Q.; Liberatore, V.; Çavuşoǧlu, M.C.; Yoo, Y. | G73: Evaluation methods of a middleware for networked surgical simulations | H73: Stud. Health Technol. Informatics | I73: 09269630 (ISSN); 1586035835 (ISBN); 978-158603583-9 (ISBN) | L73: https://www.scopus.com/inward/record.uri?eid=2-s2.0-33645747803&partnerID=40&md5=1a5087bab794d59a1a252066c7187a8c | M73: Distributed surgical virtual environments are desirable since they substantially extend the accessibility of computational resources by network communication. However, network conditions critically affects the quality of a networked surgical simulation in terms of bandwidth limit, delays, and packet losses, etc. A solution to this problem is to introduce a middleware between the simulation application and the network so that it can take actions to enhance the user-perceived simulation performance. To comprehensively assess the effectiveness of such a middleware, we propose several evaluation methods in this paper, i.e., semi-automatic evaluation, middleware overhead measurement, and usability test. © 2006 The authors. All rights reserved. | N73: 2006 | O73: 45783.3 | P73: 45783.3 | R73: 76-78 | U73: 119 | AC73: IOS Press | AE73: English | AH73: Scopus | AL73: Journal Abbreviation: Stud. Health Technol. Informatics | AP73: Virtual reality; article; Surgery; computer interface; User-Computer Interface; Software; Usability tests; evaluation; Virtual environment; medical education; surgery; Usability test; computer simulation; Computer Simulation; computer program; Computational resources; Distributed computer systems; Education, Medical; Evaluation methods; Evaluation Studies; Middleware; Network; Network communications; Network condition; Networks (circuits); Simulation applications; Simulation performance; Surgical Procedures, Operative; Surgical simulation; United States | BV73: Studies in Health Technology and Informatics
A74: exclude | B74: only questionnaires | C74: 4JK3VUTL | D74: conferencePaper | E74: 2019 | F74: Calandra, Davide; Lamberti, Fabrizio; Migliorini, Massimo | G74: On the Usability of Consumer Locomotion Techniques in Serious Games: Comparing Arm Swinging, Treadmills and Walk-in-Place | H74: 2019 IEEE 9th International Conference on Consumer Electronics (ICCE-Berlin) | I74: 978-1-7281-2745-3 | K74: 10.1109/ICCE-Berlin47944.2019.8966165 | L74: https://ieeexplore.ieee.org/document/8966165/ | N74: 43716 | O74: 45783.312 | P74: 45783.312 | Q74: 45783.312 | R74: 348-352 | X74: On the Usability of Consumer Locomotion Techniques in Serious Games | AC74: IEEE | AD74: Berlin, Germany | AF74: https://ieeexplore.ieee.org/Xplorehelp/downloads/license-information/IEEE.html | AJ74: DOI.org (Crossref) | BV74: 2019 IEEE 9th International Conference on Consumer Electronics (ICCE-Berlin)
A75: exclude | B75: only questionnaires | C75: LYM9EC8W | D75: journalArticle | E75: 2010 | F75: Cameirão, Mónica S; Badia, Sergi Bermúdez I; Oller, Esther Duarte; Verschure, Paul Fmj | G75: Neurorehabilitation using the virtual reality based Rehabilitation Gaming System: Methodology, design, psychometrics, usability and validation | H75: Journal of NeuroEngineering and Rehabilitation | J75: 1743-0003 | K75: 10.1186/1743-0003-7-48 | L75: https://jneuroengrehab.biomedcentral.com/articles/10.1186/1743-0003-7-48 | M75: Abstract Background Stroke is a frequent cause of adult disability that can lead to enduring impairments. However, given the life-long plasticity of the brain one could assume that recovery could be facilitated by the harnessing of mechanisms underlying neuronal reorganization. Currently it is not clear how this reorganization can be mobilized. Novel technology based neurorehabilitation techniques hold promise to address this issue. Here we describe a Virtual Reality (VR) based system, the Rehabilitation Gaming System (RGS) that is based on a number of hypotheses on the neuronal mechanisms underlying recovery, the structure of training and the role of individualization. We investigate the psychometrics of the RGS in stroke patients and healthy controls. Methods We describe the key components of the RGS and the psychometrics of one rehabilitation scenario called Spheroids. We performed trials with 21 acute/subacute stroke patients and 20 healthy controls to study the effect of the training parameters on task performance. This allowed us to develop a Personalized Training Module (PTM) for online adjustment of task difficulty. In addition, we studied task transfer between physical and virtual environments. Finally, we assessed the usability and acceptance of the RGS as a rehabilitation tool. Results We show that the PTM implemented in RGS allows us to effectively adjust the difficulty and the parameters of the task to the user by capturing specific features of the movements of the arms. The results reported here also show a consistent transfer of movement kinematics between physical and virtual tasks. Moreover, our usability assessment shows that the RGS is highly accepted by stroke patients as a rehabilitation tool. Conclusions We introduce a novel VR based paradigm for neurorehabilitation, RGS, which combines specific rehabilitative principles with a psychometric evaluation to provide a personalized and automated training. Our results show that the RGS effectively adjusts to the individual features of the user, allowing for an unsupervised deployment of individualized rehabilitation protocols. | N75: 2010-12 | O75: 45783.294 | P75: 45783.472 | Q75: 45783.294 | R75: 48 | T75: 1 | U75: 7 | W75: J. NeuroEng. Rehabil. | X75: Neurorehabilitation using the virtual reality based Rehabilitation Gaming System | AE75: en | AJ75: DOI.org (Crossref) | AN75: /Users/dennis/Zotero/storage/B4IQZ99Z/Cameirão et al. - 2010 - Neurorehabilitation using the virtual reality based Rehabilitation Gaming System methodology, desig.pdf | AP75: Adult; Female; Humans; Male; Middle Aged; human; adult; female; male; article; aged; reproducibility; Reproducibility of Results; algorithm; Algorithms; computer interface; physiology; User-Computer Interface; Aged; middle aged; physiotherapy; computer graphics; Computer Graphics; Physical Therapy Modalities; Psychometrics; psychometry; Software Design; Calibration; calibration; methodology; computer program; Data Interpretation, Statistical; hemiplegia; Hemiplegia; Nervous System Diseases; neurologic disease; psychomotor performance; Psychomotor Performance; recreation; statistical analysis; stroke; Stroke; Video Games
A76: exclude | B76: only questionnaires | C76: N5E6BDY6 | D76: conferencePaper | E76: 2024 | F76: Campos, Thiago Prado de; Hounsell, Marcelo da Silva; Damasceno, Eduardo Filgueiras; Valentim, Natasha M. C. | G76: Evaluating Usability, User Experience, and Playability of a Puzzle Game in Mixed Reality | H76: Proceedings of the 26th Symposium on Virtual and Augmented Reality | I76: 979-8-4007-0979-1 | K76: 10.1145/3691573.3691584 | L76: https://doi.org/10.1145/3691573.3691584 | M76: This study investigates the usability, user experience (UX), and playability of a mixed reality (MR) game called Cubism, which allows participants to interact with holograms using hand gestures. We conducted an experiment with seven participants to evaluate their interaction with the game. The Usability and User Experience Evaluation in Touchable Hologram (UUXE-ToH) questionnaire was the primary data collection instrument to capture participants’ perceptions of usability, satisfaction, and overall experience. Our findings indicate that the mixed reality environment of Cubism offers an engaging and intuitive user experience, though several challenges were identified. These insights contribute to the growing body of knowledge on human-computer interaction in mixed-reality contexts and suggest avenues for improving the design of future mixed-reality games. This research is valuable to the VR/AR/MR community by highlighting the critical factors influencing user interaction and satisfaction in MR games. | N76: 2024 | O76: 45783.306 | P76: 45783.306 | R76: 61–70 | Y76: SVR '24 | AC76: Association for Computing Machinery | AD76: New York, NY, USA | AL76: event-place: Manaus, Brazil | AP76: usability; user experience; mixed reality; playability; puzzle game
A77: exclude | B77: only questionnaires | C77: LU5QD3PP | D77: bookSection | E77: 2023 | F77: Campoverde-Durán, R.; Garzón-Vera, B. | G77: Mixed Reality: Evaluation of the User Experience to Improve the Interpretation of the Archaeological Heritage | H77: Communication and Applied Technologies | I77: 978-981-19-6346-9 978-981-19-6347-6 | L77: https://link.springer.com/10.1007/978-981-19-6347-6_48 | N77: 2023 | O77: 45783.293 | P77: 45783.293 | Q77: 45783.293 | R77: 537-546 | U77: 318 | X77: Mixed Reality | AC77: Springer Nature Singapore | AD77: Singapore | AE77: en | AJ77: DOI.org (Crossref) | AL77: Series Title: Smart Innovation, Systems and Technologies DOI: 10.1007/978-981-19-6347-6_48 | AR77: López-López, Paulo Carlos; Barredo, Daniel; Torres-Toukoumidis, Ángel; De-Santis, Andrea; Avilés, Óscar
A78: exclude | B78: irrelevant | C78: 7ZHYQ6DG | D78: conferencePaper | E78: 2021 | F78: Canelha, José; Cardoso, Jorge C. S.; Perrotta, André | G78: Usability Evaluation of a VibroTactile API for Web-Based Virtual Reality Experiences | H78: Human-Computer Interaction – INTERACT 2021: 18th IFIP TC 13 International Conference, Bari, Italy, August 30 – September 3, 2021, Proceedings, Part V | I78: 978-3-030-85606-9 | K78: 10.1007/978-3-030-85607-6_70 | L78: https://doi.org/10.1007/978-3-030-85607-6_70 | M78: This paper presents the Vibrotactile Editor System for designing and programming Vibrotactile (VT) feedback for Virtual Reality (VR) experiences. We describe the system and a usability evaluation of the programmatic component for the A-Frame web-based VR framework through a set of programming tasks. The resolution of the tasks showed some difficulty in understanding the state of the component when developing without the VT hardware present. The results show a number of potential improvements that we discuss. | N78: 2021 | O78: 45783.293 | P78: 45784.353 | R78: 517–521 | U78: 12936 | AC78: Springer-Verlag | AD78: Berlin, Heidelberg | AL78: event-place: Bari, Italy | AN78: /Users/dennis/Zotero/storage/VGA5ASM2/Canelha et al. - 2021 - Usability Evaluation of a VibroTactile API for Web-Based Virtual Reality Experiences.pdf | AP78: API; Usability evaluation; Vibrotactile feedback; Virtual Reality
A79: for-fulltext | B79: test-case generation | C79: 9ME6UB4B | D79: journalArticle | E79: 2018 | F79: Corrêa Souza, A.C.; Nunes, F.L.S.; Delamaro, M.E. | G79: An automated functional testing approach for virtual reality applications | H79: Software Testing Verification and Reliability | J79: 09600833 (ISSN) | K79: 10.1002/stvr.1690 | L79: https://www.scopus.com/inward/record.uri?eid=2-s2.0-85054803987&doi=10.1002%2fstvr.1690&partnerID=40&md5=2d16fa3aaaabec813bdc940ad54734ae | M79: Software testing is regarded as an important method for fault revealing. Despite this advantage, it has been poorly used within the scope of virtual reality (VR) applications because they are highly complex and have peculiar features. Most testing performed of this VR applications are usability, which is conducted manually and only at final of the development process. Although some works try to propose criteria for this domain, there are no approaches that automatize the generation of test data from requirements specification in the VR domain. This paper proposes an approach called virtual reality—requirements specification and testing (VR-ReST) to assist the requirements specification through a semiformal language and uses structural test criteria to generate test requirements and test data automatically for VR applications using scene graph concepts. The paper also examines the empirical results concerning the cost-effectiveness of the approach for three different VR applications through two experiments. Mutation testing was used to evaluate effectiveness. We found that the approach achieved a high mutation score outperforming random testing, by 20%, on average. Our results also demonstrate that the approach is promising since it assists in writing and validating the requirements, as well as in reducing the risks of requirement specification by adopting a semiformal language. © 2018 John Wiley & Sons, Ltd. | N79: 2018 | O79: 45783.3 | P79: 45783.3 | T79: 8 | U79: 28 | W79: Software Test Verif Reliab | AE79: English | AH79: Scopus | AL79: Publisher: John Wiley and Sons Ltd | AP79: virtual reality; Virtual reality; Cost effectiveness; Software testing; Development process; Requirements engineering; Requirements specifications; Specifications; Automated functional testing; Integrated circuit testing; Mutation testing; Requirement specification; requirements engineering; Semi-formal languages; software testing; Structural tests; Test facilities; Test requirements
A80: exclude | B80: only interviews | C80: MZNVW5KE | D80: bookSection | E80: 2019 | F80: Cao, Rui; Hou, Wenjun | G80: Research on the Interaction Design of AR Picture Books via Usability Test | H80: Human Centered Computing | I80: 978-3-030-15126-3 978-3-030-15127-0 | L80: http://link.springer.com/10.1007/978-3-030-15127-0_53 | N80: 2019 | O80: 45783.294 | P80: 45783.294 | Q80: 45783.294 | R80: 524-534 | U80: 11354 | AC80: Springer International Publishing | AD80: Cham | AE80: en | AJ80: DOI.org (Crossref) | AL80: Series Title: Lecture Notes in Computer Science DOI: 10.1007/978-3-030-15127-0_53 | AR80: Tang, Yong; Zu, Qiaohong; Rodríguez García, José G.
A81: exclude | B81: irrelevant | C81: 98UT64BZ | D81: conferencePaper | E81: 2024 | F81: Capdevila, M.G.; Vitorino, N.; Poledna, Y.; Malena, B.; Drechsler, M.F.; Albuquerque, G.G.; Furlan, T.; Netto, R.S. | G81: Smart&Safe Mobility Lab: Mixed Reality Environment with HIL, CV2X for VRU Detection | H81: IEEE Int. Conf. Cloud Netw., CloudNet | I81: 979-835037656-2 (ISBN) | K81: 10.1109/CloudNet62863.2024.10815791 | L81: https://www.scopus.com/inward/record.uri?eid=2-s2.0-85217081280&doi=10.1109%2fCloudNet62863.2024.10815791&partnerID=40&md5=134dcb34822952ff50bd3de94a5818eb | M81: This work proposes the development of a Mixed Reality Environment (MRE) designed to facilitate Hardware-in-the-Loop (HIL) testing through the simulation of Advanced Driver Assistance Systems (ADAS). The proposed infrastructure will enable the connection of a vehicle to a simulator, which will project images of the virtual environment onto a surface, providing the driver with an immersive experience while oper-ating the connected vehicle. The developed infrastructure will have the capability to directly acquire data from various types of simulated sensor models commonly used in ADAS systems, such as cameras, RADARs, and LiDARs. This setup will be instrumental in evaluating and studying user experience by analyzing driver behavior in response to different interfaces and alert systems. Additionally, the vehicle will be integrated into the vehicular communication network, allowing for comprehensive hardware and software testing in scenarios that pose risks to the physical integrity of the driver and Vulnerable Road Users (VRUs), such as vehicle collisions and areas with frequent VRU crossings. © 2024 IEEE. | N81: 2024 | O81: 45783.3 | P81: 45783.3 | AC81: Institute of Electrical and Electronics Engineers Inc. | AE81: English | AH81: Scopus | AL81: Journal Abbreviation: IEEE Int. Conf. Cloud Netw., CloudNet | AP81: Virtual environments; Virtualization; Digital storage; Automated driving; Automobile testing; Highway accidents; Mixed reality; Advanced driver assistance systems; Advanced driver assistances; Analog storage; Automated Driving; Automobile driver simulators; Cellular vehicle to everything; Cellular Vehicle to Everything; Cellulars; Driver-assistance systems; Hardware-in-the-loop simulation; Magnetic levitation vehicles; Mixed Reality; Mixed-reality environment; Road users; Safe mobility; Sensor stimulation; Sensor Stimulation | AR81: Menezes Ferrazani Mattos D.; Monteiro Moraes I.; Nguyen T.M.T.; de Souza Couto R.; Rubinstein R.G. | BV81: 2024 IEEE 13th International Conference on Cloud Networking, CloudNet 2024
A82: for-fulltext | B82: face tracking | C82: 2NT2DWRA | D82: conferencePaper | E82: 2020 | F82: Hynes, E.; Flynn, R.; Lee, B.; Murray, N. | G82: An Evaluation of Lower Facial Micro Expressions as an Implicit QoE Metric for an Augmented Reality Procedure Assistance Application | H82: Ir. Signals Syst. Conf., ISSC | I82: 978-172819418-9 (ISBN) | K82: 10.1109/ISSC49989.2020.9180173 | L82: https://www.scopus.com/inward/record.uri?eid=2-s2.0-85092691294&doi=10.1109%2fISSC49989.2020.9180173&partnerID=40&md5=82fa28f9fb380be1c8c813d831fb5d37 | M82: Augmented reality (AR) has been identified as a key technology to enhance worker utility in the context of increasing automation of repeatable procedures. AR can achieve this by assisting the user in performing complex and frequently changing procedures. Crucial to the success of procedure assistance AR applications is user acceptability, which can be measured by user quality of experience (QoE). An active research topic in QoE is the identification of implicit metrics that can be used to continuously infer user QoE during a multimedia experience. A user's QoE is linked to their affective state. Affective state is reflected in facial expressions. Emotions shown in micro facial expressions resemble those expressed in normal expressions but are distinguished from them by their brief duration. The novelty of this work lies in the evaluation of micro facial expressions as a continuous QoE metric by means of correlation analysis to the more traditional and accepted post-experience self-reporting. In this work, an optimal Rubik's Cube solver AR application was used as a proof of concept for complex procedure assistance. This was compared with a paper-based procedure assistance control. QoE expressed by affect in normal and micro facial expressions was evaluated through correlation analysis with post-experience reports. The results show that the AR application yielded higher task success rates and shorter task durations. Micro facial expressions reflecting disgust correlated moderately to the questionnaire responses for instruction disinterest in the AR application. © 2020 IEEE. | N82: 2020 | O82: 45783.3 | P82: 45783.3 | AC82: Institute of Electrical and Electronics Engineers Inc. | AE82: English | AH82: Scopus | AL82: Journal Abbreviation: Ir. Signals Syst. Conf., ISSC | AP82: augmented reality; Augmented reality; Facial Expressions; User experience; Proof of concept; Correlation methods; Experience report; affective state; Complex procedure; Correlation analysis; Key technologies; micro facial expression; Micro-expressions; Multimedia systems; quality of experience; Quality of experience (QoE); Quality of service | BV82: 2020 31st Irish Signals and Systems Conference, ISSC 2020
A83: exclude | B83: only questionnaires | C83: WL2RYWWK | D83: conferencePaper | E83: 2022 | F83: Casteleiro-Pitrez, Joana | G83: Augmented Reality Books: A User Experience Evaluation | H83: Design, User Experience, and Usability: UX Research, Design, and Assessment: 11th International Conference, DUXU 2022, Held as Part of the 24th HCI International Conference, HCII 2022, Virtual Event, June 26 – July 1, 2022, Proceedings, Part I | I83: 978-3-031-05896-7 | K83: 10.1007/978-3-031-05897-4_25 | L83: https://doi.org/10.1007/978-3-031-05897-4_25 | M83: The rise of information society and the profound mediatization phenomenon led to a book use decrease. On the other hand, the attempt to promote book use and widen the capacities of the traditional book led to the application of computational resources, one of these resources is Augmented Reality (AR).This study is about AR published Books and their User Experience (UX). We want to know if publishing AR books shows sufficient UX. We chose three AR books published in Portugal and applied a quantitative empirical study to evaluate their UX and answer this research question. Sixty users read the AR books and then answered the User Experience Questionnaire (UEQ) used as the research instrument of this study. We also compare the results with a benchmark. The results show a positive evaluation in almost all the means of the scales of the three AR books. Only in one book do we find a neutral evaluation in the scales of Stimulation and Novelty. Regarding the benchmark, the scales Attractiveness, Novelty and Stimulation achieved Excellent/Good category levels. On the other hand, the pragmatic quality aspects like Perspicuity, Dependably, and Efficiency revels a below “Good category” level, emphasizing the urgent need to improve the UX of AR books. | N83: 2022 | O83: 45783.293 | P83: 45784.35 | R83: 353–368 | U83: 13321 | X83: Augmented Reality Books | AC83: Springer-Verlag | AD83: Berlin, Heidelberg | AL83: Series Title: Lecture Notes in Computer Science DOI: 10.1007/978-3-031-05897-4_25 | AP83: Augmented reality books; User experience; User experience questionnaire
A84: exclude | B84: only heuristics | C84: LCS2RA9K | D84: journalArticle | E84: 2013 | F84: Castilla, Diana; Garcia-Palacios, Azucena; BretóN-LóPez, Juana; Miralles, Ignacio; BañOs, Rosa MaríA; Etchemendy, Ernestina; Farfallini, Luis; Botella, Cristina | G84: Process of design and usability evaluation of a telepsychology web and virtual reality system for the elderly: Butler | H84: Int. J. Hum.-Comput. Stud. | J84: 1071-5819 | K84: 10.1016/j.ijhcs.2012.10.017 | L84: https://doi.org/10.1016/j.ijhcs.2012.10.017 | M84: Butler is a multi-application system based on Internet technology and virtual reality, designed to meet the needs of elderly users. Its objectives are to assist elderly populations in accessing technology and new forms of communication, replicating, as far as possible the way of lineal interaction that this population group had traditionally to interact with information in order to facilitate the first contacts with technology. Butler is equipped with e-mail, videoconferencing, blogging, access to the Internet through a well-known web search engine, image and sound gallery, new contacts searcher, and two virtual reality environments. In this paper we describe Butler's most relevant features taking into account the usability design process and the usability evaluation of the system, which, after pilot testing, have proven to be highly acceptable and satisfactory to users. We also present the results of evaluations pertaining to the iconography used in the program, the navigation and users' help design process, and the first functional prototype, all of which were designed and redesigned with the aid of web heuristics and guidelines for the web design for elderly users. Results suggest important features to be taken into account when designing and developing this sort of application for the elderly. | N84: 2013-03 | O84: 45783.306 | P84: 45783.306 | R84: 350–362 | T84: 3 | U84: 71 | AL84: Place: USA Publisher: Academic Press, Inc. | AP84: Usability; Virtual reality; Elderly; Digital divide; Social network; Social networking service
A85: exclude | B85: only questionnaires | C85: MIT4ACLK | D85: conferencePaper | E85: 2023 | F85: Catenazzi, Nadia; Sommaruga, Lorenzo; Locatelli, Chiara | G85: Usability Evaluation of Mixed Reality Applications in VET Training | H85: Extended Reality: International Conference, XR Salento 2023, Lecce, Italy, September 6-9, 2023, Proceedings, Part I | I85: 978-3-031-43400-6 | K85: 10.1007/978-3-031-43401-3_27 | L85: https://doi.org/10.1007/978-3-031-43401-3_27 | M85: This paper presents a usability study of wearable and handheld Mixed Reality and hypervideo technologies to support procedural learning in the vocational education and training context. As a case study an application based on the Tangram game was developed for HoloLens 2, Android smartphones and hypervideo. The app is structured as a procedural learning activity with incremental levels of scaffolding. The usability of these applications was evaluated in a user testing involving 90 students. No remarkable difference has emerged among the three applications in terms of completion rate during the learning process, but in the retention and transfer tasks HoloLens 2 users performed worse than users of the other devices. Considering the time on task metric, HoloLens 2 users time was aligned with hypervideo, while smartphone users generally took more time, probably because smartphones are not hand-free devices. An expert review was also conducted, providing a number of suggestions for improvements, mainly concerning the interaction design, and the positioning of holograms in the physical space. In the comparison among the devices, none was clearly preferred over the other: HoloLens 2 presented higher attractiveness, motivation of use, sense of immersion, but also greater cognitive load; handheld devices resulted easy to use but required considerable physical effort in activities where they needed to be hold for a long time. Hypervideo was easy to access, with an intuitive interaction, but less attractive. | N85: 2023 | O85: 45783.293 | P85: 45784.354 | R85: 410–423 | U85: 14218 | AC85: Springer-Verlag | AD85: Berlin, Heidelberg | AL85: event-place: Lecce, Italy | AP85: handheld MR; hypervideo; Interaction; Usability; User experience; wearable MR
A86: for-fulltext | B86: automation unclear, read fulltext | C86: WKH5URFQ | D86: journalArticle | E86: 2021 | F86: Cannavo, Alberto; Calandra, Davide; Prattico, F. Gabriele; Gatteschi, Valentina; Lamberti, Fabrizio | G86: An Evaluation Testbed for Locomotion in Virtual Reality | H86: IEEE Transactions on Visualization and Computer Graphics | J86: 1077-2626, 1941-0506, 2160-9306 | K86: 10.1109/TVCG.2020.3032440 | L86: https://ieeexplore.ieee.org/document/9234004/ | N86: 44256 | O86: 45783.313 | P86: 45783.313 | Q86: 45783.313 | R86: 1871-1889 | T86: 3 | U86: 27 | W86: IEEE Trans. Visual. Comput. Graphics | AF86: https://ieeexplore.ieee.org/Xplorehelp/downloads/license-information/IEEE.html | AJ86: DOI.org (Crossref) | AN86: /Users/dennis/Zotero/storage/FFRHLABK/Cannavo et al. - 2021 - An Evaluation Testbed for Locomotion in Virtual Reality.pdf
A87: for-fulltext | B87: Event-based | C87: 7TF6TGVQ | D87: conferencePaper | E87: 2019 | F87: Che, Xiaoping; Ma, Siqi; Yu, Qi; Yue, Chenfeng | G87: An Event-Based User Experience Evaluation Method for Virtual Reality Applications | H87: 2019 IEEE SmartWorld, Ubiquitous Intelligence & Computing, Advanced & Trusted Computing, Scalable Computing & Communications, Cloud & Big Data Computing, Internet of People and Smart City Innovation (SmartWorld/SCALCOM/UIC/ATC/CBDCom/IOP/SCI) | I87: 978-1-7281-4034-6 | K87: 10.1109/SmartWorld-UIC-ATC-SCALCOM-IOP-SCI.2019.00164 | L87: https://ieeexplore.ieee.org/document/9060384/ | N87: 2019-08 | O87: 45783.312 | P87: 45783.312 | Q87: 45783.312 | R87: 767-774 | AC87: IEEE | AD87: Leicester, United Kingdom | AF87: https://ieeexplore.ieee.org/Xplorehelp/downloads/license-information/IEEE.html | AJ87: DOI.org (Crossref) | BV87: 2019 IEEE SmartWorld, Ubiquitous Intelligence & Computing, Advanced & Trusted Computing, Scalable Computing & Communications, Cloud & Big Data Computing, Internet of People and Smart City Innovation (SmartWorld/SCALCOM/UIC/ATC/CBDCom/IOP/SCI)
A88: exclude | B88: irrelevant | C88: A3WYX2M5 | D88: conferencePaper | E88: 2023 | F88: Chalimas, Theodoros; Mania, Katerina | G88: Cross-Device Augmented Reality Systems for Fire and Rescue based on Thermal Imaging and Live Tracking | H88: 2023 IEEE International Symposium on Mixed and Augmented Reality Adjunct (ISMAR-Adjunct) | I88: 979-8-3503-2891-2 | K88: 10.1109/ISMAR-Adjunct60411.2023.00018 | L88: https://ieeexplore.ieee.org/document/10322255/ | N88: 45215 | O88: 45783.312 | P88: 45783.312 | Q88: 45783.312 | R88: 50-54 | AC88: IEEE | AD88: Sydney, Australia | AF88: https://doi.org/10.15223/policy-029 | AJ88: DOI.org (Crossref) | BV88: 2023 IEEE International Symposium on Mixed and Augmented Reality Adjunct (ISMAR-Adjunct)
A89: for-fulltext | B89: sentiment | C89: X7GAG9RM | D89: conferencePaper | E89: 2019 | F89: Sanchis-Font, R.; Castro-Bleda, M.J.; González, J.-Á. | G89: Applying Sentiment Analysis with Cross-Domain Models to Evaluate User eXperience in Virtual Learning Environments | H89: Lect. Notes Comput. Sci. | I89: 03029743 (ISSN); 978-303020520-1 (ISBN) | K89: 10.1007/978-3-030-20521-8_50 | L89: https://www.scopus.com/inward/record.uri?eid=2-s2.0-85067512228&doi=10.1007%2f978-3-030-20521-8_50&partnerID=40&md5=4c17f34f7e8766564317fb862007da62 | M89: Virtual Learning Environments are growing in importance as fast as e-learning is becoming highly demanded by universities and students all over the world. This paper investigates how to automatically evaluate User eXperience in this domain. Two Learning Management Systems have been evaluated, one system is an ad-hoc system called “Conecto” (in Spanish and English languages), and the other one is an open-source Moodle personalized system (in Spanish). We have applied machine learning tools to all the comments given by a total of 133 users (37 English speakers and 96 Spanish speakers) to obtain their polarity (positive, negative, or neutral) using cross-domain models trained with a corpus of a different domain (tweets for each language) and general models for the language. The obtained results are very promising and they give an insight to keep going the research of applying sentiment analysis tools on User eXperience evaluation. This is a pioneering idea to provide a better and accurate understanding on human needs in the interaction with Virtual Learning Environments. The ultimate goal is to develop further tools of automatic feed-back of user perception for designing Virtual Learning Environments centered in user’s emotions, beliefs, preferences, perceptions, responses, behaviors and accomplishments that occur before, during and after the interaction. © 2019, Springer Nature Switzerland AG. | N89: 2019 | O89: 45783.3 | P89: 45783.3 | R89: 609-620 | U89: 11506 LNCS | AC89: Springer Verlag | AE89: English | AH89: Scopus | AL89: Journal Abbreviation: Lect. Notes Comput. Sci. | AP89: Virtual reality; Data mining; E-learning; Learning systems; Behavioral research; User experience; User experience evaluations; Computer aided instruction; User eXperience; Machine learning; Applied machine learning; Cross-domain models; English languages; Learning management system; Learning Management Systems; Neural networks; Open systems; Polarity; Sentiment analysis; Virtual learning environments; Virtual Learning Environments | AR89: Joya G.; Rojas I.; Catala A. | BV89: Lecture Notes in Computer Science (including subseries Lecture Notes in Artificial Intelligence and Lecture Notes in Bioinformatics)
A90: exclude | B90: only questionnaires + interviews | C90: YXH5VKFT | D90: journalArticle | E90: 2015 | F90: Chen, Chwen Jen; Lau, Siew Yung; Teh, Chee Siong | G90: A feasible group testing framework for producing usable virtual reality learning applications | H90: Virtual Real. | J90: 1359-4338 | K90: 10.1007/s10055-015-0263-7 | L90: https://doi.org/10.1007/s10055-015-0263-7 | M90: Designing a usable learning application is one of the key factors in ensuring effective learning. This article introduces modified group usability testing (MGUT) as a feasible framework for evaluating the usability of non-immersive virtual reality (VR) learning applications. Conventionally, usability testing of such learning applications often employs the one-to-one approach in which an evaluator conducts testing with several individual participants. As opposed to the one-to-one approach, the group approach involves several-to-many participants performing tasks simultaneously, with several evaluators observing and interacting with participants. This article describes the complete step-by-step procedure for conducting MGUT to uncover usability problems of a VR learning application that aims to educate its users on fire safety and prevention. It also proposes methods to analyze these usability problems. The effectiveness and efficiency of MGUT was then compared with DGUT, the original group testing technique and cooperative evaluation (CE), which is a typical one-to-one approach. Results indicate that all three techniques are able to reveal usability problems of different usability factors and show similar capability to discover the most critical and serious problems. MGUT is more effective than DGUT as it can collect additional usability problems of various factors and of different levels of severity. MGUT is as effective as CE as both techniques can identify usability problems which are more or less comparable in terms of quantity and quality. As for efficiency, MGUT and DGUT are more efficient than CE as these group testing approaches require lesser testing time, lesser effort in terms of the intensive interaction with participants although with slight more effort in the preparation of the physical setting. In addition, it is also obvious that MGUT and DGUT involve richer participation than CE. MGUT is also more feasible than DGUT as it allows some flexibility in the computer arrangement setting. | N90: 2015-06 | O90: 45783.306 | P90: 45783.306 | R90: 129–144 | T90: 2 | U90: 19 | AL90: Place: Berlin, Heidelberg Publisher: Springer-Verlag | AP90: Virtual reality; Group usability testing; Human—computer interface; Interactive learning environments
A91: for-fulltext | B91: agent based | C91: E5XKGQCR | D91: conferencePaper | E91: 2019 | F91: Stahlke, S.; Nova, A.; Mirza-Babaei, P. | G91: Artificial playfulness: A tool for automated agent-based playtesting | H91: Conf Hum Fact Comput Syst Proc | I91: 978-145035971-9 (ISBN) | K91: 10.1145/3290607.3313039 | L91: https://www.scopus.com/inward/record.uri?eid=2-s2.0-85067300618&doi=10.1145%2f3290607.3313039&partnerID=40&md5=cd050b114ab43e2e185f53df1e4a199e | M91: Usertesting is commonly employed in games user research (GUR) to understand the experience of players interacting with digital games. However, recruitment and testing with human users can be laborious and resource-intensive, particularly for independent developers. To help mitigate these obstacles, we are developing a framework for simulated testing sessions with agents driven by artificial intelligence (AI). Specifically, we aim to imitate the navigation of human players in a virtual world. By mimicking the tendency of users to wander, explore, become lost, and so on, these agents may be used to identify basic issues with a game's world and level design, enabling informed iteration earlier in the development process. Here, we detail our progress in developing a framework for configurable agent navigation and simple visualization of simulated data. Ultimately, we hope to provide a basis for the development of a tool for simulation-driven usability testing in games. © 2019 Copyright held by the owner/author(s). | N91: 2019 | O91: 45783.3 | P91: 45783.3 | AC91: Association for Computing Machinery | AE91: English | AH91: Scopus | AL91: Journal Abbreviation: Conf Hum Fact Comput Syst Proc | AP91: Virtual reality; Data visualization; Artificial Intelligence; Usability testing; Human engineering; Artificial intelligence; Interactive computer graphics; Software design; Human computer interaction; Human-Computer Interaction; Development process; User testing; Automated agents; Computer games; Game development; Game Development; Games user researches; Playtesting; Simulated testing; Usertesting | BV91: Conference on Human Factors in Computing Systems - Proceedings
A92: exclude | B92: only questionnaires | C92: C3Y57GKQ | D92: journalArticle | E92: 2019 | F92: Choi, Young Mi | G92: Applying tangible augmented reality for product usability assessment | H92: J. Usability Studies | M92: When developing a new product, it is common for designers to feel that they do not have enough information about users' needs. This is especially true at the front end of a new product design process. An important component of this process is testing and validating potential design concepts. The aim of this study was to explore the validity of augmented reality (AR) and tangible augmented reality (TAR) as tools for evaluating the usability of a product. For this study, 70 college students were recruited to perform a usability evaluation of a space heater product and equivalent AR and TAR representations of it. The results indicate that overall TAR can be a reliable method for evaluating the usability of a fully realized product, especially for products with physical interface controls. However, TAR was not found to be reliable with respect to Ease of Use. Overall, AR was not found to be as reliable as TAR or with respect to any specific aspect of usability that was measured. Applications, limitations, and areas for further study are discussed in this article as well. | N92: 2019-08 | O92: 45783.306 | P92: 45783.306 | R92: 187–200 | T92: 4 | U92: 14 | AL92: Place: Bloomingdale, IL Publisher: Usability Professionals' Association | AP92: augmented reality; usability assessment; product design evaluation; tangible augmented reality
A93: exclude | B93: irrelevant | C93: K5GAJHRR | D93: conferencePaper | E93: 2024 | F93: Christakis, S.; Makris, N.; Korakis, T.; Fdida, S. | G93: On the Automated Scaling of User Plane Function for 5G: An Experimental Evaluation | H93: Jt. Eur. Conf. Networks Commun. 6G Summit, EuCNC/6G Summit | I93: 979-835034499-8 (ISBN) | K93: 10.1109/EuCNC/6GSummit60053.2024.10597110 | L93: https://www.scopus.com/inward/record.uri?eid=2-s2.0-85199929065&doi=10.1109%2fEuCNC%2f6GSummit60053.2024.10597110&partnerID=40&md5=eb0806a9788b8adfac91464f8c9d6732 | M93: The advent of emerging technologies like autonomous vehicles, AR/VR, IoT, smart cities, etc., have raised the bar in terms of dealing with enormous data transfer, high speeds, and low response times. 5G has been designed and is optimized unceasingly to try to meet these demands. The quick evolution of 5G Radio Access Network (RAN) technologies has ushered in a new era of connectivity and communication. This has caused the 5G Core Network to face significant problems, as on many occasions, the RAN's ability to transmit data overwhelms the core network's ability to handle it. As a result, network congestion occurs, leading to reduced network speeds, significant delays, and occasional disruptions, which have a profound effect on low-quality user experience. This issue has triggered the scientific community to investigate ways to enhance the performance of the 5G core network, to match with the evolving demands of RAN technologies. In this work, we present an innovative algorithm for dynamic management and optimization of 5G network resources within a Kubernetes cluster environment. The algorithm's functionality revolves around monitoring metrics of User Plane Function (UPF) and making real-time decisions on deploying multiple UPFs within the cluster to ensure enhanced network performance and cost optimization. © 2024 IEEE. | N93: 2024 | O93: 45783.3 | P93: 45783.3 | R93: 979-984 | AC93: Institute of Electrical and Electronics Engineers Inc. | AE93: English | AH93: Scopus | AL93: Journal Abbreviation: Jt. Eur. Conf. Networks Commun. 6G Summit, EuCNC/6G Summit | AP93: 5G mobile communication systems; 5G Network; Clustering algorithms; Core Network; Core networks; Data transfer; Dynamic algorithm; Dynamic Algorithm; Emerging technologies; Experimental evaluation; Kubernetes; Network technologies; Queueing networks; Radio access networks; Scaling; Scalings; UPF; User plane function; User planes | BV93: 2024 Joint European Conference on Networks and Communications and 6G Summit, EuCNC/6G Summit 2024
A94: exclude | B94: only questionnaires | C94: 4GC8RXZK | D94: journalArticle | E94: 2023 | F94: Chu, C.-H.; Liu, Y.-L. | G94: Augmented reality user interface design and experimental evaluation for human-robot collaborative assembly | H94: Journal of Manufacturing Systems | J94: 02786125 (ISSN) | K94: 10.1016/j.jmsy.2023.04.007 | L94: https://www.scopus.com/inward/record.uri?eid=2-s2.0-85153212322&doi=10.1016%2fj.jmsy.2023.04.007&partnerID=40&md5=20c12f1a9180146b4f5b3d250b8338f1 | M94: Artificial intelligence (AI) has been applied to a wide spectrum of industrial sectors, but manual operations remain indispensable in most manufacturing systems due to high complexity or costs involving in automation. A more practical approach is enabling humans to collaborate with machines complementary to each other. One critical issue in human-robot collaboration (HRC) is to assure the operator's productivity, safety, and trust while interacting with the robot. This paper presents an experimental study on user interface design in augmented reality (AR) for human-robot collaborative assembly in a shared workspace. The experiment aims to verify and cross-compare the effectiveness of visual and haptic cues in various forms that convey the robot intent to human. Analysis of the work performance and gazing behavior of participants shows that both cues can reduce their visual attention on the moving robot during the collaboration. The interface that provides the proximity of robot using visual cues is considered most useful. It is not intuitive to recognize complex information by vibration on different parts of the human hand in the experiment. Finally, human trust to robot has a higher correlation on the usability of a user interface than the work performance assisted by the interface. These findings may work as design guidelines for AR assisted human-robot interaction in smart manufacturing. © 2023 The Society of Manufacturing Engineers | N94: 2023 | O94: 45783.3 | P94: 45783.3 | R94: 313-324 | U94: 68 | W94: J Manuf Syst | AE94: English | AH94: Scopus | AL94: Publisher: Elsevier B.V. | AP94: Experimental evaluation; Augmented reality; Human robot interaction; Human-robot collaboration; Human robots; User interfaces; Behavioral research; Manual assembly; Machine design; Design evaluation; Collaborative assembly; Sensory cues; User interface; User interface designs; Wide spectrum; Work performance
A95: for-fulltext | B95: automation unclear, read fulltext | C95: RG4KGU9J | D95: conferencePaper | E95: 2018 | F95: Wienrich, Carolin; Döllinger, Nina; Kock, Simon; Schindler, Kristina; Traupe, Ole | G95: Assessing User Experience in Virtual Reality – A Comparison of Different Measurements | H95: Design, User Experience, and Usability: Theory and Practice: 7th International Conference, DUXU 2018, Held as Part of HCI International 2018, Las Vegas, NV, USA, July 15-20, 2018, Proceedings, Part I | I95: 978-3-319-91796-2 | K95: 10.1007/978-3-319-91797-9_41 | L95: https://doi.org/10.1007/978-3-319-91797-9_41 | M95: As other interactive technologies, the promising virtual reality (VR) applications and their success highly depend on the quality of the user’s experience. The present study gives first insights into relations between general and VR specific aspects of user experience by: (1) Analyzing the evaluation requirements for a large-scale multi-user use case; (2) relating evaluation concepts from the fields of (2D) user experience (UX) and (3D) VR experiences; (3) testing these relations by incorporating measurements from different research fields, and (4) discussing implications for a holistic evaluation framework. During and after experiencing a multi-user adventure on the Immersive Deck of Illusion Walk, participants rated their experience with respect to various components of general UX as well as other components specific to VR experiences. The results revealed positive correlations of presence and social presence with most of the employed post-experience UX measures. The relations between the post- and in-experience measurements showed some inconsistencies. Overall, the experience was positively appraised. The results encourage further investigations into integrating measurements from different lines of research in order to explore the evaluation space of VR experiences. | N95: 2018 | O95: 45783.306 | P95: 45783.306 | R95: 573–589 | AC95: Springer-Verlag | AD95: Berlin, Heidelberg | AL95: event-place: Las Vegas, NV, USA | AP95: Virtual reality; User experience; Evaluation framework
A96: exclude | B96: only questionnaires | C96: YS3UWCQI | D96: journalArticle | E96: 2022 | F96: Clement, P.; Veledar, O.; Könczöl, C.; Danzinger, H.; Posch, M.; Eichberger, A.; Macher, G. | G96: Enhancing Acceptance and Trust in Automated Driving trough Virtual Experience on a Driving Simulator | H96: Energies | J96: 19961073 (ISSN) | K96: 10.3390/en15030781 | L96: https://www.scopus.com/inward/record.uri?eid=2-s2.0-85123044552&doi=10.3390%2fen15030781&partnerID=40&md5=9cbd4fc53f4db38d60956510e2df4c4a | M96: As vehicle driving evolves from human-controlled to autonomous, human–machine interaction ensures intuitive usage as well as the feedback from vehicle occupants to the machine for optimising controls. The feedback also improves understanding of the user satisfaction with the system behaviour, which is crucial for determining user trust and, hence, the acceptance of the new functionalities that aim to improve mobility solutions and increase road safety. Trust and acceptance are potentially the crucial parameters for determining the success of autonomous driving deployment in wider society. Hence, there is a need to define appropriate and measurable parameters to be able to quantify trust and acceptance in a physically safe environment using dependable methods. This study seeks to support technical developments and data gathering with psychology to determine the degree to which humans trust automated driving functionalities. The primary aim is to define if the usage of an advanced driving simulator can improve consumer trust and acceptance of driving automation through tailor-made studies. We also seek to measure significant differences in responses from different demographic groups. The study employs tailor-made driving scenarios to gather feedback on trust, usability and user workload of 55 participants monitoring the vehicle behaviour and environment during the automated drive. Participants’ subjective ratings are gathered before and after the simulator session. Results show a significant increase in trust ensuing the exposure to the driving automation functionalities. We quantify this increase resulting from the usage of the driving simulator. Those less experienced with driving automation show a higher increase in trust and, therefore, profit more from the exercise. This appears to be linked to the demanded participant workload, as we establish a link between workload and trust. The findings provide a noteworthy contribution to quantifying the method of evaluating and ensuring user acceptance of driving automation. It is only through the increase of trust and consequent improvement of user acceptance that the introduction of the driving automation into wider society will be a guaranteed success. © 2022 by the authors. Licensee MDPI, Basel, Switzerland. | N96: 2022 | O96: 45783.3 | P96: 45783.3 | T96: 3 | U96: 15 | W96: Energies | AE96: English | AH96: Scopus | AL96: Publisher: MDPI | AP96: Automation; Virtual reality; NASA; System usability; Digital storage; Automated driving; Automobile drivers; Case-studies; Advanced driver assistance systems; Automobile simulators; Driving simulator; Feedback; Motor transportation; Acceptance; Vehicles; Advanced driver assistant system; Advanced driver assistant systems; Advanced driver assistant systems (ADAS); Automated driving (AD); Driving school; Expression of trust; NASA TLX; NASA-TLX; Simulator case study; System usability scale
A97: exclude | B97: only questionnaires | C97: MWD9YWND | D97: journalArticle | E97: 2024 | F97: Colombo, E.; Regli, L.; Esposito, G.; Germans, M.R.; Fierstra, J.; Serra, C.; Sebök, M.; Van Doormaal, T. | G97: Mixed Reality for Cranial Neurosurgical Planning: A Single-Center Applicability Study with the First 107 Subsequent Holograms | H97: Operative Neurosurgery | J97: 23324252 (ISSN) | K97: 10.1227/ons.0000000000001033 | L97: https://www.scopus.com/inward/record.uri?eid=2-s2.0-85190832780&doi=10.1227%2fons.0000000000001033&partnerID=40&md5=55a3e002df6063869b03f7977f40f3b1 | M97: BACKGROUND AND OBJECTIVES:Mixed reality (MxR) benefits neurosurgery by improving anatomic visualization, surgical planning and training. We aim to validate the usability of a dedicated certified system for this purpose.METHODS:All cases prepared with MxR in our center in 2022 were prospectively collected. Holographic rendering was achieved using an incorporated fully automatic algorithm in the MxR application, combined with contrast-based semiautomatic rendering and/or manual segmentation where necessary. Hologram segmentation times were documented. Visualization during surgical preparation (defined as the interval between finalized anesthesiological induction and sterile draping) was performed using MxR glasses and direct streaming to a side screen. Surgical preparation times were compared with a matched historical cohort of 2021. Modifications of the surgical approach after 3-dimensional (3D) visualization were noted. Usability was assessed by evaluating 7 neurosurgeons with more than 3 months of experience with the system using a Usefulness, Satisfaction and Ease of use (USE) questionnaire.RESULTS:One hundred-seven neurosurgical cases prepared with a 3D hologram were collected. Surgical indications were oncologic (63/107, 59%), cerebrovascular (27/107, 25%), and carotid endarterectomy (17/107, 16%). Mean hologram segmentation time was 39.4 ± 20.4 minutes. Average surgical preparation time was 48.0 ± 17.3 minutes for MxR cases vs 52 ± 17 minutes in the matched 2021 cohort without MxR (mean difference 4, 95% CI 1.7527-9.7527). Based on the 3D hologram, the surgical approach was modified in 3 cases. Good usability was found by 57% of the users.CONCLUSION:The perioperative use of 3D holograms improved direct anatomic visualization while not significantly increasing intraoperative surgical preparation time. Usability of the system was adequate. Further technological development is necessary to improve the automatic algorithms and reduce the preparation time by circumventing manual and semiautomatic segmentation. Future studies should focus on quantifying the potential benefits in teaching, training, and the impact on surgical and functional outcomes. © 2024 Lippincott Williams and Wilkins. All rights reserved. | N97: 2024 | O97: 45783.3 | P97: 45783.3 | R97: 551-558 | T97: 5 | U97: 26 | W97: Oper. Neurosurg. | AE97: English | AH97: Scopus | AL97: Publisher: Lippincott Williams and Wilkins | AP97: Article; automation; human; adult; augmented reality; Augmented reality; cohort analysis; prospective study; demographics; image segmentation; Mixed reality; questionnaire; Surgical planning; surgical training; algorithm; patient satisfaction; nuclear magnetic resonance imaging; 3D visualization; anesthesia induction; anesthetic agent; aneurysm clipping; arteriovenous malformation; brain lateral ventricle; brain surgery; bypass surgery; carotid endarterectomy; cerebrovascular surgery; computed tomographic angiography; cranial sinus; craniotomy; descriptive research; elective surgery; external carotid artery; glioma; hypophysis adenoma; internal carotid artery; meningioma; metastasis; neurosurgeon; neurosurgery; Neurosurgery; skull; surgical approach; temporal artery; three-dimensional imaging
A98: exclude | B98: irrelevant | C98: FXUUSAWK | D98: journalArticle | E98: 2024 | F98: Colombo, G.; Minta, K.; Grübel, J.; Tai, W.L.E.; Hölscher, C.; Schinazi, V.R. | G98: Detecting cognitive impairment through an age-friendly serious game: The development and usability of the spatial performance assessment for cognitive evaluation (SPACE) | H98: Computers in Human Behavior | J98: 07475632 (ISSN) | K98: 10.1016/j.chb.2024.108349 | L98: https://www.scopus.com/inward/record.uri?eid=2-s2.0-85198013886&doi=10.1016%2fj.chb.2024.108349&partnerID=40&md5=7f266a297a7ecf97f388b0b518a57224 | M98: The Spatial Performance Assessment for Cognitive Evaluation (SPACE) is a novel iPad serious game designed to identify differences in spatial ability indicative of early signs of cognitive impairment. This paper reports on the development of SPACE and presents the results from three usability studies across different ages. Study 1 compared the traditional tap and swipe control interface with a semiautomated interface. Study 2 investigated the benefits of a UI widget that displayed the rotation performed in the Virtual Environment (VE). Study 3 evaluated the effects of a simplified configuration of landmarks explored in the VE. Findings across the studies indicated that age was the primary factor influencing performance. Younger participants consistently outperformed older ones across various tasks and reported higher usability and lower workload. Despite notable performance improvements for the tasks in SPACE, the new control interface, UI widget, and simplified configuration only had a minimal impact on usability. Younger participants rated SPACE above the level of mature products, while older participants found it useable but not always engaging. Critically, the significant interactions between age and experimental conditions indicated that younger and older participants benefited differently from the design modifications. Here, the semi-automated control, the simplified configuration, and, to a lesser extent, the UI widget showed promise in mitigating age-related performance differences while maintaining the level of challenge necessary to assess differences in cognitive status. This research showcases the potential of SPACE as a serious game and emphasises the importance of balancing simplicity with task demands for future unsupervised deployment. © 2024 The Authors | N98: 2024 | O98: 45783.3 | P98: 45783.3 | U98: 160 | W98: Comput. Hum. Behav. | AE98: English | AH98: Scopus | AL98: Publisher: Elsevier Ltd | AP98: Usability engineering; Usability studies; Automation; Age-friendly; Ageing; Cognitive impairment; Control interfaces; Digital assessment; Performance; Performance assessment; Serious games; Spatial abilities; Spatial ability; Spatial performance; Usability; Virtual reality
A99: exclude | B99: only questionnaires | C99: SH7AAM4T | D99: conferencePaper | E99: 2024 | F99: Constantinides, Nicolas; Constantinides, Argyris; Koukopoulos, Dimitrios; Fidas, Christos; Belk, Marios | G99: CulturAI: Exploring Mixed Reality Art Exhibitions with Large Language Models for Personalized Immersive Experiences | H99: Adjunct Proceedings of the 32nd ACM Conference on User Modeling, Adaptation and Personalization | I99: 979-8-4007-0466-6 | K99: 10.1145/3631700.3664874 | L99: https://doi.org/10.1145/3631700.3664874 | M99: Mixed Reality (MR) technologies have transformed the way in which we interact and engage with digital content, offering immersive experiences that blend the physical and virtual worlds. Over the past years, there has been increasing interest in employing Artificial Intelligence (AI) technologies to improve user experience and trustworthiness in cultural contexts. However, the integration of Large Language Models (LLMs) into MR applications within the Cultural Heritage (CH) domain is relatively underexplored. In this work, we present an investigation into the integration of LLMs within MR environments, focusing on the context of virtual art exhibitions. We implemented a HoloLens MR application, which enables users to explore artworks while interacting with an LLM through voice. To evaluate the user experience and perceived trustworthiness of individuals engaging with an LLM-based virtual art guide, we adopted a between-subject study design, in which participants were randomly assigned to either the LLM-based version or a control group using conventional interaction methods. The LLM-based version allows users to pose inquiries about the artwork displayed, ranging from details about the creator to information about the artwork’s origin and historical significance. This paper presents the technical aspects of integrating LLMs within MR applications and evaluates the user experience and perceived trustworthiness of this approach in enhancing the exploration of virtual art exhibitions. Results of an initial evaluation provide evidence about the positive aspect of integrating LLMs in MR applications. Findings of this work contribute to the advancement of MR technologies for the development of future interactive personalized art experiences. | N99: 2024 | O99: 45783.306 | P99: 45783.306 | R99: 102–105 | Y99: UMAP Adjunct '24 | AC99: Association for Computing Machinery | AD99: New York, NY, USA | AL99: event-place: Cagliari, Italy | AP99: Mixed Reality; User Study; User Experience Evaluation; Large Language Models
A100: for-fulltext | B100: usability evaluation unclear, read fulltext | C100: EXAE8MG2 | D100: journalArticle | E100: 2019 | F100: Naylor, Matthew; Morrison, Ben; Ridout, Brad; Campbell, Andrew | G100: Augmented Experiences: Investigating the Feasibility of Virtual Reality as Part of a Workplace Wellbeing Intervention | H100: Interacting with Computers | J100: 0953-5438, 1873-7951 | K100: 10.1093/iwc/iwz033 | L100: https://academic.oup.com/iwc/article/31/5/507/5643592 | M100: Abstract This exploratory experiment tested the effect of two virtual reality (VR) relaxation interventions on measures of physiological arousal and affect, compared to a control. Forty-nine participants were randomly assigned to one of three conditions, all using the Oculus Rift. Participants wore a heart rate (HR) monitor and completed pre- and post-test surveys, including the positive and negative affect schedule, Likert-type and open feedback questions. Mixed repeated measures ANOVAs revealed significant reductions in HR and affect over time across all conditions, with a significant interaction identified for the breathing condition’s effect on negative affect. Participants were able to identify feeling relaxation, as well as influencing factors. Further, the majority expected, and supported, the introduction of VR interventions in their workplace and/or college, with privacy being a common concern. These results demonstrate the potential of VR augmented relaxation interventions with recommendations for further study provided. RESEARCH HIGHLIGHTS VR can potentially provide wellbeing interventions with a uniquely immersive quality Results suggest interactive and immersive VR experiences may facilitate relaxation and reduce stress Participants believe there may be substantial benefits to having VR wellbeing interventions at work and college. | N100: 43754 | O100: 45783.313 | P100: 45783.313 | Q100: 45783.313 | R100: 507-523 | T100: 5 | U100: 31 | X100: Augmented Experiences | AE100: en | AF100: https://academic.oup.com/journals/pages/open_access/funder_policies/chorus/standard_publication_model | AJ100: DOI.org (Crossref)
...

Sheet Full Text Screening
A1: Include | B1: Notes Abstract Screening | C1: Notes | D1: Author | E1: Title | F1: Publication Year | G1: Methodology Notes | H1: Usability Dimension Notes | I1: Baseline | J1: Sample Size | K1: XR Technology | L1: Measurement Notes
A2: include | B2: =_xlfn.XLOOKUP(E2,'Title Abstract Screening'!G:G,'Title Abstract Screening'!B:B,"") -> physiological factors | C2: heart beat | D2: Döllinger, Nina; Beck, Matthias; Wolf, Erik; Mal, David; Botsch, Mario; Latoschik, Marc Erich; Wienrich, Carolin | E2: “If It’s Not Me It Doesn’t Make a Difference” - The Impact of Avatar Personalization on user Experience and Body Awareness in Virtual Reality | F2: 2023 | G2: HCT | H2: interoceptive accuracy | I2: SMS Mind Questionnaire | J2: 86 | K2: VR | L2: heart rate
A3: include | B3: =_xlfn.XLOOKUP(E3,'Title Abstract Screening'!G:G,'Title Abstract Screening'!B:B,"") -> usability evaluation unclear, read fulltext | C3: time tracking with step count | D3: Nakamura, Ricardo; Lago, Lucas L. M.; Carneiro, Alexandre B.; Cunha, Anderson J. C.; Ortega, Fábio J. M.; Bernardes, João L.; Tori, Romero | E3: 3PI experiment: immersion in third-person view | F3: 2010 | G3: time between decisions (steps) in the game | H3: not mentioned, guessed effectiveness/efficiency | J3: 8 out of 47 | K3: AR | L3: time
A4: include | B4: =_xlfn.XLOOKUP(E4,'Title Abstract Screening'!G:G,'Title Abstract Screening'!B:B,"") -> multimodal ux NN | C4: read again for final extraction | D4: Pannattee, Peerawat; Shimada, Shogo; Yem, Vibol; Nishiuchi, Nobuyuki | E4: A deep learning framework for automatic assessment of presence in virtual reality using multimodal behavioral cues | F4: 2025 | G4: multimodal UX NN | H4: UX
A5: include | B5: =_xlfn.XLOOKUP(E5,'Title Abstract Screening'!G:G,'Title Abstract Screening'!B:B,"") -> physiological factors | C5: flow | D5: Bian, Yulong; Yang, Chenglei; Gao, Fengqiang; Li, Huiyu; Zhou, Shisheng; Li, Hanchao; Sun, Xiaowen; Meng, Xiangxu | E5: A framework for physiological indicators of flow in VR games: construction and preliminary evaluation | F5: 2016 | G5: physiological measures | H5: flow through: cardiovascular function, respiration, and ZM electromyography | I5: Flow Short Scale | J5: 36 | K5: VR | L5: Cardiac activity, Thoracic respiration, Muscle tone
A6: include | B6: =_xlfn.XLOOKUP(E6,'Title Abstract Screening'!G:G,'Title Abstract Screening'!B:B,"") -> automation unclear, read fulltext | C6: head movement | D6: Seffah, Ahmed; Benn, Jonathan; Mammar, Halima Habieb | E6: A low-cost test environment for usability studies of head-mounted virtual reality systems | F6: 2008 | G6: Navigation and viewpoint control interaction | H6: Interaction/ lernability | J6: 2 | K6: VR | L6: Head Movement
A7: exclude duplicate | B7: =_xlfn.XLOOKUP(E7,'Title Abstract Screening'!G:G,'Title Abstract Screening'!B:B,"") -> physiological factors | C7: duplicate, A framework for physiological indicators of flow in VR games: construction and preliminary evaluation | D7: Bian, Yulong; Yang, Chenglei; Gao, Fengqiang; Li, Hanchao; Sun, Xiaowen; Meng, Xiangxu; Wang, Yu | E7: A Physiological Evaluation Model for Flow-Experience in VR Games: Construction and Preliminary Test | F7: 2015
A8: include | B8: =_xlfn.XLOOKUP(E8,'Title Abstract Screening'!G:G,'Title Abstract Screening'!B:B,"") -> head rotation frequency | D8: Hynes, E.; Flynn, R.; Lee, B.; Murray, N. | E8: A QoE Evaluation of an Augmented Reality Procedure Assistance Application | F8: 2020 | G8: high frequency head rotation | H8: proxy for the degree of delight or annoyance | I8: paper based alternative | J8: 48 | K8: AR | L8: high frequency head rotation in pitch yaw and roll directions
A9: exclude | B9: =_xlfn.XLOOKUP(E9,'Title Abstract Screening'!G:G,'Title Abstract Screening'!B:B,"") -> usability evaluation unclear, read fulltext | C9: no automated usability evaluation | D9: Suomela, Riku; Lehikoinen, Juha; Salminen, Ilkka | E9: A System for Evaluating Augmented Reality User Interfaces in Wearable Computers | F9: 2001 | K9: AR
A10: exclude | B10: =_xlfn.XLOOKUP(E10,'Title Abstract Screening'!G:G,'Title Abstract Screening'!B:B,"") -> automation unclear, read fulltext | C10: no automated usability evaluation | D10: Woo, J.; Shidara, K.; Achard, C.; Tanaka, H.; Nakamura, S.; Pelachaud, C. | E10: Adaptive virtual agent: Design and evaluation for real-time human-agent interaction | F10: 2024 | G10: Head Rotation | H10: - | I10: - | J10: 60 | K10: -
A11: include | B11: =_xlfn.XLOOKUP(E11,'Title Abstract Screening'!G:G,'Title Abstract Screening'!B:B,"") -> agent based | C11: agent based, but only introductionof technique | D11: Prada, Rui; Prasetya, I. S. W. B.; Kifetew, Fitsum; Dignum, Frank; Vos, Tanja E. J.; Lander, Jason; Donnart, Jean-yves; Kazmierowski, Alexandre; Davidson, Joseph; Fernandes, Pedro M. | E11: Agent-based Testing of Extended Reality Systems | F11: 2020 | G11: software agents | K11: XR | L11: only introduction of technique
A12: exclude | B12: =_xlfn.XLOOKUP(E12,'Title Abstract Screening'!G:G,'Title Abstract Screening'!B:B,"") -> usability evaluation unclear, read fulltext | C12: no usability evaluation | D12: Zou, L.; Liang, T. | E12: Algorithm Optimization of Computer Simulation Vehicle Driving Simulation System Based on Virtual Reality Technology | F12: 2024
A13: include | B13: =_xlfn.XLOOKUP(E13,'Title Abstract Screening'!G:G,'Title Abstract Screening'!B:B,"") -> physiological factors | C13: EEG, head movement for correlation of viewpoint to EEG | D13: He, Linjia; Li, Hongsong; Xue, Tong; Sun, Deyuan; Zhu, Shoulun; Ding, Gangyi | E13: Am I in the theater? usability study of live performance based virtual reality | F13: 2018 | G13: EEG | H13: Engagement | I13: TV vs VR | J13: 25 | K13: VR | L13: EEG, head movement
A14: exclude | B14: =_xlfn.XLOOKUP(E14,'Title Abstract Screening'!G:G,'Title Abstract Screening'!B:B,"") -> test-case generation | C14: no usability evaluation | D14: Corrêa Souza, A.C.; Nunes, F.L.S.; Delamaro, M.E. | E14: An automated functional testing approach for virtual reality applications | F14: 2018
A15: include | B15: =_xlfn.XLOOKUP(E15,'Title Abstract Screening'!G:G,'Title Abstract Screening'!B:B,"") -> face tracking | C15: micro expressions | D15: Hynes, E.; Flynn, R.; Lee, B.; Murray, N. | E15: An Evaluation of Lower Facial Micro Expressions as an Implicit QoE Metric for an Augmented Reality Procedure Assistance Application | F15: 2020 | G15: face tracking | H15: QoE | I15: questionnaire, normal facial expression | J15: 48 | K15: AR | L15: micro facial expressions
A16: include | B16: =_xlfn.XLOOKUP(E16,'Title Abstract Screening'!G:G,'Title Abstract Screening'!B:B,"") -> automation unclear, read fulltext | C16: read again for final extraction | D16: Cannavo, Alberto; Calandra, Davide; Prattico, F. Gabriele; Gatteschi, Valentina; Lamberti, Fabrizio | E16: An Evaluation Testbed for Locomotion in Virtual Reality | F16: 2021 | G16: Heart Rate and Calculations | H16: Accuracy, Operation Speed, Error Proneness | J16: 48 | K16: VR
A17: include | B17: =_xlfn.XLOOKUP(E17,'Title Abstract Screening'!G:G,'Title Abstract Screening'!B:B,"") -> Event-based | C17: Correlation of events to heart beat | D17: Che, Xiaoping; Ma, Siqi; Yu, Qi; Yue, Chenfeng | E17: An Event-Based User Experience Evaluation Method for Virtual Reality Applications | F17: 2019 | G17: Heart Rate and Correlation To Grab, Touch Operate and move | H17: UX | I17: - | J17: 80 | K17: VR | L17: Heart Rate and Success Rate while capturing game events
